{"artist_name": "林宥嘉",
 "song_name": "我总是一个人在练习一个人",
 "song_id": "108284",
 "song_lyric": "作曲 : 陈小霞\n 作词 : 李焯雄\n一个人去上班 又一个人去吃饭\n再和更多的一个人纠缠\n话才说到一半 没有人听完\n我不孤单 孤单只是 情绪泛滥\n\n一个人出去逛 又一个人躺在床\n这晚有多少的一个人没伴\n不够分另一半 爱已经用完\n我不孤单 孤单只是 不够果断\n\n我总是一个人 在练习一个人\n寂寞是脚跟 回忆是凹痕 也没有人见证\n我总是一个人 在练习一个人\n寂寞是脚跟 回忆是凹痕 我一个人共存\n\n我总是一个人 在练习一个人\n寂寞是脚跟 回忆是凹痕 也没有人见证\n我总是一个人 在练习一个人\n寂寞是脚跟 回忆是凹痕 我一个人共存\n\n没有人在等着一个人\n一个人在等着没有人\n没有人在等着没有人",
 "pic_url": "http://p1.music.126.net/nJlpALEtfmeFzb_k8RkDuQ==/109951163177954238.jpg",
 "words": ["作曲",
 "陈",
 "小",
 "霞",
 "作词",
 "李",
 "焯",
 "雄",
 "一个",
 "个人",
 "去",
 "上班",
 "又",
 "一个",
 "个人",
 "去",
 "吃饭",
 "再",
 "和",
 "更多",
 "的",
 "一个",
 "个人",
 "纠缠",
 "话",
 "才",
 "说",
 "到",
 "一半",
 "没有",
 "有人",
 "听完",
 "我",
 "不",
 "孤单",
 "孤单",
 "只是",
 "情绪",
 "泛滥",
 "一个",
 "个人",
 "出去",
 "去逛",
 "又",
 "一个",
 "个人",
 "躺",
 "在",
 "床",
 "这",
 "晚",
 "有",
 "多少",
 "的",
 "一个",
 "个人",
 "没",
 "伴",
 "不够",
 "分",
 "另一半",
 "一半",
 "爱",
 "已经",
 "用",
 "完",
 "我",
 "不",
 "孤单",
 "孤单",
 "只是",
 "不够",
 "果断",
 "我",
 "总是",
 "一个",
 "个人",
 "在",
 "练习",
 "一个",
 "个人",
 "寂寞",
 "是",
 "脚跟",
 "回忆",
 "是",
 "凹痕",
 "也",
 "没有",
 "有人",
 "见证",
 "我",
 "总是",
 "一个",
 "个人",
 "在",
 "练习",
 "一个",
 "个人",
 "寂寞",
 "是",
 "脚跟",
 "回忆",
 "是",
 "凹痕",
 "我",
 "一个",
 "个人",
 "共存",
 "我",
 "总是",
 "一个",
 "个人",
 "在",
 "练习",
 "一个",
 "个人",
 "寂寞",
 "是",
 "脚跟",
 "回忆",
 "是",
 "凹痕",
 "也",
 "没有",
 "有人",
 "见证",
 "我",
 "总是",
 "一个",
 "个人",
 "在",
 "练习",
 "一个",
 "个人",
 "寂寞",
 "是",
 "脚跟",
 "回忆",
 "是",
 "凹痕",
 "我",
 "一个",
 "个人",
 "共存",
 "没有",
 "有人",
 "在",
 "等",
 "着",
 "一个",
 "个人",
 "一个",
 "个人",
 "在",
 "等",
 "着",
 "没有",
 "有人",
 "没有",
 "有人",
 "在",
 "等",
 "着",
 "没有",
 "有人"]}