{"artist_name": "李健",
"song_name": "凌晨两点",
"song_id": "110009",
"song_lyric":
 "我在凌晨两点想你\n想你此刻会在哪里\n\n哪里都比不过我心里\n\n心里随时随地有你\n\n在想你\n\n想你就会出现在我的眼里\n\n在眼里\n\n在我眼里你是我的唯一\n\n我的生活不能没你\n\n没你就会失去很多\n\n很多事我也不清楚\n\n清楚的是我很爱你\n\n很爱你\n\n爱你就会为你不停的歌唱\n\n在歌唱\n\n歌唱在我生命中遇见你\n\n在想你\n\n想你就会出现在我的眼里\n\n在眼里\n\n在我眼里你是我的唯一\n\n很爱你\n\n爱你就会为你大声的歌唱\n\n在歌唱\n\n歌唱在我生命中遇见你\n\n凌晨两点",
"pic_url": "http://p1.music.126.net/aSxiiy01L3Q35IqsaAUgvQ==/100055558133714.jpg",
"words": ["我", "在", "凌晨", "两点", "想", "你", "想", "你", "此刻", "会", "在", "哪里", "哪里", "都", "比", "不过", "我心", "心里", "心里", "随时", "随时随地", "随地", "有", "你", "在", "想", "你", "想", "你", "就", "会", "出现", "现在", "我", "的", "眼里", "在", "眼里", "在", "我", "眼里", "你", "是", "我", "的", "唯一", "我", "的", "生活", "不能", "没", "你", "没", "你", "就", "会", "失去", "很多", "很多", "事", "我", "也", "不", "清楚", "清楚", "的", "是", "我", "很", "爱", "你", "很", "爱", "你", "爱", "你", "就", "会", "为", "你", "不停", "的", "歌唱", "在", "歌唱", "歌唱", "在", "我", "生命", "命中", "遇见", "你", "在", "想", "你", "想", "你", "就", "会", "出现", "现在", "我", "的", "眼里", "在", "眼里", "在", "我", "眼里", "你", "是", "我", "的", "唯一", "很", "爱", "你", "爱", "你", "就", "会", "为", "你", "大声", "的", "歌唱", "在", "歌唱", "歌唱", "在", "我", "生命", "命中", "遇见", "你", "凌晨", "两点"]}