{"artist_name": "李圣杰",
 "song_name": "Now & Forever",
 "song_id": "114769",
 "song_lyric": "狂欢前的骚动\n你和我和他和他准备 放纵\n心情很high 脚步很fun\n狂欢音乐想喝醉\n迷乱的城太多不安灵魂\n 在等待救赎\nand now闭上你的双眼\n用耳朵去看去拥抱整个世界\n体验心的音乐\nNow and forever\nCause only you can know\n闭上你的双眼\n用耳朵去看去拥抱整个世界\n跟着自己心跳\nNow and forever\n没人能改变 Oo~\n尽情拥抱 你的欲望\n享受party的热光\n音乐国里不必暗自悲伤\n跟我大声唱\nand now 闭上你的双眼\n用耳朵去看去拥抱整个世界\n跟着自己心跳\nNow and forever\n没有人能改变 Oo~",
 "pic_url": "http://p1.music.126.net/ytX85T9ry_P8FQ2WMExJaw==/109951163106175865.jpg",
 "words": ["狂欢",
 "前",
 "的",
 "骚动",
 "你",
 "和",
 "我",
 "和",
 "他",
 "和",
 "他",
 "准备",
 "放纵",
 "心情",
 "很",
 "high",
 "脚步",
 "很",
 "狂欢",
 "欢音",
 "音乐",
 "想",
 "喝醉",
 "迷乱",
 "的",
 "城",
 "太多",
 "不安",
 "安灵",
 "灵魂",
 "在",
 "等待",
 "救赎",
 "now",
 "闭",
 "上",
 "你",
 "的",
 "双眼",
 "用",
 "耳朵",
 "去",
 "看去",
 "拥抱",
 "整个",
 "世界",
 "体验",
 "心",
 "的",
 "音乐",
 "and",
 "only",
 "you",
 "can",
 "闭",
 "上",
 "你",
 "的",
 "双眼",
 "用",
 "耳朵",
 "去",
 "看去",
 "拥抱",
 "整个",
 "世界",
 "跟着",
 "自己",
 "心跳",
 "and",
 "没人",
 "能",
 "改变",
 "Oo",
 "尽情",
 "拥抱",
 "你",
 "的",
 "欲望",
 "享受",
 "party",
 "的",
 "热",
 "光",
 "音乐",
 "国",
 "里",
 "不必",
 "暗自",
 "自悲",
 "悲伤",
 "跟",
 "我",
 "大声",
 "唱",
 "now",
 "闭",
 "上",
 "你",
 "的",
 "双眼",
 "用",
 "耳朵",
 "去",
 "看去",
 "拥抱",
 "整个",
 "世界",
 "跟着",
 "自己",
 "心跳",
 "and",
 "没有",
 "有人",
 "能",
 "改变",
 "Oo"]}