{"artist_name": "王杰",
 "song_name": "孤星",
 "song_id": "156644",
 "song_lyric": "天空没有一片云 眼中没有泪滴\n不回头不说一句 要拿出自己拼到底\n紧握的手永远也不会躲\n不管多少险恶会来找我\n倔强的心什么也不想留\n任凭在风中 OH\n天地只剩一个我昂然孤独地走\n多少心都已离去 多少人还在看着戏\n是否我早已习惯一种名字叫孤单\n是否我注定挂在最冷的夜空那段\n别问我 有没有明天\n就让我 一个人面对\n我的梦 不会再是一场错\n别问我 知心还有谁\n就让我 留着你的吻\n我的歌 将永远陪着你走\n(music)",
 "pic_url": "http://p1.music.126.net/48Rrt1JHa8lm07JwP_2l-A==/18981968742213622.jpg",
 "words": ["天空",
 "没有",
 "一片",
 "云",
 "眼中",
 "没有",
 "泪滴",
 "不",
 "回头",
 "不",
 "说",
 "一句",
 "要",
 "拿出",
 "出自",
 "自己",
 "拼到",
 "拼到底",
 "到底",
 "紧握",
 "的",
 "手",
 "永远",
 "也",
 "不会",
 "躲",
 "不管",
 "多少",
 "险恶",
 "会来",
 "找",
 "我",
 "倔强",
 "的",
 "心",
 "什么",
 "也",
 "不想",
 "留",
 "任凭",
 "在",
 "风",
 "中",
 "天地",
 "只",
 "剩",
 "一个",
 "我",
 "昂然",
 "孤独",
 "地",
 "走",
 "多少",
 "心",
 "都",
 "已",
 "离去",
 "多少",
 "人",
 "还",
 "在",
 "看着",
 "戏",
 "是否",
 "我",
 "早已",
 "习惯",
 "一种",
 "名字",
 "叫",
 "孤单",
 "是否",
 "我",
 "注定",
 "挂",
 "在",
 "最冷",
 "的",
 "夜空",
 "那段",
 "别",
 "问",
 "我",
 "有没有",
 "没有",
 "明天",
 "就让",
 "我",
 "一个",
 "个人",
 "人面",
 "面对",
 "我",
 "的",
 "梦",
 "不会",
 "再",
 "是",
 "一场",
 "错",
 "别",
 "问",
 "我",
 "知心",
 "还有",
 "谁",
 "就让",
 "我",
 "留",
 "着",
 "你",
 "的",
 "吻",
 "我",
 "的",
 "歌",
 "将",
 "永远",
 "陪",
 "着",
 "你",
 "走",
 "music"]}