{"artist_name": "蔡依林",
 "song_name": "花蝴蝶",
 "song_id": "209583",
 "song_lyric": "作曲 : Anders Kjer/David Clewett/Alice Gernandt\n 作词 : 严云农\n环游了世界 全世界\n却发现美丽没有旗舰店\n谁穿着钉鞋 不肯变\n\n停止了自转 变成一个茧\n你我都希望特别\n又不敢太过于特别 yeah\n流行是一种安全\n搔着闷骚的太阳穴\n你是花花世界里 限量版的花花蝴蝶\n美女们只是比较豁出去 比较敢一点\n花蝴蝶的美的艳的炫 若没三审定谳\n那些路人甲们 凭什么发言惹人讨厌\n快离开冬眠 赶快破茧\n别被无聊困在地球表面\n想灵魂出窍 甩平凡嘴脸\n就自创品牌 靠自己变脸\n当你不刻意特别\n突然就会变得特别 yeah\n只要别越描越黑\n你的眼睛就会放电\n你是花花世界里 限量版的花花蝴蝶\n美女们只是比较豁出去 比较敢一点\n花蝴蝶的美的艳的炫 若没三审定谳\n那些路人甲们 凭什么发言惹人讨厌\n你可以瞬间飞去东京巴黎米兰纽约\n别让别人嘴里的形容词左右你视野\n如果有人的魅力足够为这世纪代言\n那是她敢站出来 变成蝴蝶飞舞翩翩\n你是花花世界里 限量版的花花蝴蝶\n美女们只是比较豁出去 比较敢一点\n花蝴蝶的美的艳的炫 若没三审定谳\n那些路人甲们 凭什么发言惹人讨厌（准备惊艳）\n你可以身穿花花 限量的花蝴蝶\n你可以比你想象中再爱炫 再敢一点\n你可以自己决定 没得最后三审定谳\n你可以让路人甲 闭嘴惊艳\n你是花花世界里 限量版的花花蝴蝶\n美女们只是比较豁出去 比较敢一点\n花蝴蝶的美的艳的炫 若没三审定谳\n那些路人甲们 凭什么发言惹人讨厌（准备惊艳）",
 "pic_url": "http://p1.music.126.net/NiYweRAAwG8KdqAs5HeucA==/109951163061824205.jpg",
 "words": ["作曲",
 "Anders",
 "Kjer",
 "David",
 "Clewett",
 "Alice",
 "作词",
 "严",
 "云",
 "农",
 "环游",
 "了",
 "世界",
 "全世界",
 "世界",
 "却",
 "发现",
 "美丽",
 "没有",
 "旗舰",
 "旗舰店",
 "谁",
 "穿着",
 "钉鞋",
 "不肯",
 "变",
 "停止",
 "了",
 "自转",
 "变成",
 "一个",
 "茧",
 "你",
 "我",
 "都",
 "希望",
 "特别",
 "又",
 "不敢",
 "太",
 "过于",
 "特别",
 "流行",
 "是",
 "一种",
 "安全",
 "搔",
 "着",
 "闷骚",
 "的",
 "太阳",
 "太阳穴",
 "你",
 "是",
 "花花",
 "花花世界",
 "世界",
 "里",
 "限量",
 "限量版",
 "的",
 "花花",
 "花蝴蝶",
 "蝴蝶",
 "美女",
 "们",
 "只是",
 "比较",
 "豁出",
 "豁出去",
 "出去",
 "比较",
 "敢",
 "一点",
 "花蝴蝶",
 "蝴蝶",
 "的",
 "美的",
 "艳",
 "的",
 "炫",
 "若",
 "没",
 "三审",
 "审定",
 "谳",
 "那些",
 "路人",
 "路人甲",
 "们",
 "凭",
 "什么",
 "发言",
 "惹人讨厌",
 "讨厌",
 "快",
 "离开",
 "开冬",
 "冬眠",
 "赶快",
 "破",
 "茧",
 "别",
 "被",
 "无聊",
 "困",
 "在",
 "地球",
 "地球表面",
 "表面",
 "想",
 "灵魂",
 "出",
 "窍",
 "甩",
 "平凡",
 "嘴脸",
 "就",
 "自创",
 "品牌",
 "靠",
 "自己",
 "变脸",
 "当",
 "你",
 "不",
 "刻意",
 "特别",
 "突然",
 "就",
 "会",
 "变得",
 "特别",
 "只要",
 "别",
 "越描越黑",
 "你",
 "的",
 "眼睛",
 "就",
 "会",
 "放电",
 "你",
 "是",
 "花花",
 "花花世界",
 "世界",
 "里",
 "限量",
 "限量版",
 "的",
 "花花",
 "花蝴蝶",
 "蝴蝶",
 "美女",
 "们",
 "只是",
 "比较",
 "豁出",
 "豁出去",
 "出去",
 "比较",
 "敢",
 "一点",
 "花蝴蝶",
 "蝴蝶",
 "的",
 "美的",
 "艳",
 "的",
 "炫",
 "若",
 "没",
 "三审",
 "审定",
 "谳",
 "那些",
 "路人",
 "路人甲",
 "们",
 "凭",
 "什么",
 "发言",
 "惹人讨厌",
 "讨厌",
 "你",
 "可以",
 "瞬间",
 "飞去",
 "东京",
 "巴黎",
 "米兰",
 "纽约",
 "别",
 "让",
 "别人",
 "嘴里",
 "的",
 "形容",
 "形容词",
 "左右",
 "你",
 "视野",
 "如果",
 "有人",
 "的",
 "魅力",
 "足够",
 "为",
 "这",
 "世纪",
 "代言",
 "那",
 "是",
 "她",
 "敢",
 "站出",
 "出来",
 "变成",
 "蝴蝶",
 "飞舞",
 "翩翩",
 "你",
 "是",
 "花花",
 "花花世界",
 "世界",
 "里",
 "限量",
 "限量版",
 "的",
 "花花",
 "花蝴蝶",
 "蝴蝶",
 "美女",
 "们",
 "只是",
 "比较",
 "豁出",
 "豁出去",
 "出去",
 "比较",
 "敢",
 "一点",
 "花蝴蝶",
 "蝴蝶",
 "的",
 "美的",
 "艳",
 "的",
 "炫",
 "若",
 "没",
 "三审",
 "审定",
 "谳",
 "那些",
 "路人",
 "路人甲",
 "们",
 "凭",
 "什么",
 "发言",
 "惹人讨厌",
 "讨厌",
 "准备",
 "惊艳",
 "你",
 "可以",
 "身穿",
 "花花",
 "限量",
 "的",
 "花蝴蝶",
 "蝴蝶",
 "你",
 "可以",
 "比",
 "你",
 "想象",
 "中",
 "再",
 "爱",
 "炫",
 "再",
 "敢",
 "一点",
 "你",
 "可以",
 "自己",
 "决定",
 "没得",
 "最后",
 "三审",
 "审定",
 "谳",
 "你",
 "可以",
 "让路",
 "路人",
 "路人甲",
 "闭嘴",
 "惊艳",
 "你",
 "是",
 "花花",
 "花花世界",
 "世界",
 "里",
 "限量",
 "限量版",
 "的",
 "花花",
 "花蝴蝶",
 "蝴蝶",
 "美女",
 "们",
 "只是",
 "比较",
 "豁出",
 "豁出去",
 "出去",
 "比较",
 "敢",
 "一点",
 "花蝴蝶",
 "蝴蝶",
 "的",
 "美的",
 "艳",
 "的",
 "炫",
 "若",
 "没",
 "三审",
 "审定",
 "谳",
 "那些",
 "路人",
 "路人甲",
 "们",
 "凭",
 "什么",
 "发言",
 "惹人讨厌",
 "讨厌",
 "准备",
 "惊艳"]}