{"artist_name": "蔡琴",
"song_name": "夜上海",
"song_id": "210760",
"song_lyric":
 "夜上海 夜上海 你是个不夜城\n华灯起 车声响 歌舞升平\n\n只见她 笑脸迎 谁知她内心苦闷\n夜生活 都为了 衣食住行\n\n酒不醉人 人自醉\n胡天胡地 磋跎了青春\n\n晓色朦胧 倦眼惺忪\n大家归去 心灵儿随着转动的车轮\n\n换一换 新天地 别有一个新环境\n回味着 夜生活 如梦初醒\n\n夜上海 夜上海 你是个不夜城\n华灯起 车声响 歌舞升平\n\n只见她 笑脸迎 谁知她内心苦闷\n夜生活 都为了 衣食住行\n\n酒不醉人 人自醉\n胡天胡地 磋跎了青春\n\n晓色朦胧 倦眼惺忪\n大家归去 心灵儿随着转动的车轮\n\n换一换 新天地 别有一个新环境\n回味着 夜生活 如梦初醒",
"pic_url": "http://p1.music.126.net/6IjRFLSHPC-atyqNDKhnJQ==/3317226581078615.jpg",
"words": ["夜", "上海", "夜", "上海", "你", "是", "个", "不夜城", "华灯", "起", "车声", "声响", "歌舞", "歌舞升平", "升平", "只见", "她", "笑脸", "迎", "谁知", "她", "内心", "心苦", "苦闷", "夜生活", "生活", "都", "为了", "衣食", "衣食住行", "酒不醉", "醉人", "人", "自", "醉", "胡天", "胡天胡地", "胡地", "磋", "跎", "了", "青春", "晓色", "朦胧", "倦", "眼", "惺忪", "大家", "归去", "心灵", "儿", "随着", "转动", "的", "车轮", "换", "一", "换", "新天地", "天地", "别", "有", "一个", "新", "环境", "回味", "着", "夜生活", "生活", "如梦初醒", "夜", "上海", "夜", "上海", "你", "是", "个", "不夜城", "华灯", "起", "车声", "声响", "歌舞", "歌舞升平", "升平", "只见", "她", "笑脸", "迎", "谁知", "她", "内心", "心苦", "苦闷", "夜生活", "生活", "都", "为了", "衣食", "衣食住行", "酒不醉", "醉人", "人", "自", "醉", "胡天", "胡天胡地", "胡地", "磋", "跎", "了", "青春", "晓色", "朦胧", "倦", "眼", "惺忪", "大家", "归去", "心灵", "儿", "随着", "转动", "的", "车轮", "换", "一", "换", "新天地", "天地", "别", "有", "一个", "新", "环境", "回味", "着", "夜生活", "生活", "如梦初醒"]}