{"artist_name": "陈慧琳",
 "song_name": "假天真",
 "song_id": "215317",
 "song_lyric": "作词 : 林夕\n尽你气力说爱我\n我怕会听错\n回忆只得这个\n冯两耳去收录\n不算多\n尽你努力答应我\n你会爱惜我\n如粉笔字擦过\n仍有数秒钟感动过\n假的好处\n随手分些给我\n不要等\n假的兴奋\n仍叫我太开心\n真天真\n假天真\n我怕我忘了怎么区分\n七分假\n三分真\n也够我共你一次又一次热吻\n若你有话要了决\n对我耳边说\n留低一点温暖\n融化我这一双黑眼圈\n极有礼貌对我说\n你要断一断\n还肯亲自解决\n还说我有更好\n可以选\n假的好处\n随手分些给我\n不要等\n假的兴奋\n仍叫我太开心\n真天真\n假天真\n我怕我忘了怎么区分\n七分假\n三分真\n也够我共你一次又一次热吻\nmusic\n真天真\n假天真\n我怕我忘了怎么区分\n七分假\n三分真\n也够我共你一次又一次热吻\n真天真\n假天真\n我怕我忘了怎么区分\n七分假\n三分真\n也够我共你一次又一次热吻",
 "pic_url": "http://p1.music.126.net/XFfHqLmk54PPMERswTEi-g==/799344953393492.jpg",
 "words": ["作词",
 "林",
 "夕",
 "尽",
 "你",
 "气力",
 "说",
 "爱",
 "我",
 "我",
 "怕",
 "会",
 "听错",
 "回忆",
 "只得",
 "这个",
 "冯",
 "两耳",
 "去",
 "收录",
 "不算",
 "多",
 "尽",
 "你",
 "努力",
 "答应",
 "我",
 "你",
 "会",
 "爱惜",
 "我",
 "如",
 "粉笔",
 "笔字",
 "擦",
 "过",
 "仍",
 "有数",
 "数秒",
 "秒钟",
 "感动",
 "过",
 "假",
 "的",
 "好处",
 "随手",
 "分",
 "些",
 "给",
 "我",
 "不要",
 "等",
 "假",
 "的",
 "兴奋",
 "仍",
 "叫",
 "我",
 "太",
 "开心",
 "真",
 "天真",
 "假",
 "天真",
 "我",
 "怕",
 "我",
 "忘",
 "了",
 "怎么",
 "区分",
 "七分",
 "假",
 "三分",
 "真",
 "也",
 "够",
 "我",
 "共",
 "你",
 "一次",
 "又",
 "一次",
 "热吻",
 "若",
 "你",
 "有",
 "话",
 "要",
 "了",
 "决",
 "对",
 "我",
 "耳边",
 "说",
 "留",
 "低",
 "一点",
 "温暖",
 "融化",
 "我",
 "这",
 "一双",
 "黑眼",
 "黑眼圈",
 "眼圈",
 "极",
 "有",
 "礼貌",
 "对",
 "我",
 "说",
 "你",
 "要",
 "断",
 "一断",
 "还",
 "肯",
 "亲自",
 "自解",
 "解决",
 "还",
 "说",
 "我",
 "有",
 "更好",
 "可以",
 "选",
 "假",
 "的",
 "好处",
 "随手",
 "分",
 "些",
 "给",
 "我",
 "不要",
 "等",
 "假",
 "的",
 "兴奋",
 "仍",
 "叫",
 "我",
 "太",
 "开心",
 "真",
 "天真",
 "假",
 "天真",
 "我",
 "怕",
 "我",
 "忘",
 "了",
 "怎么",
 "区分",
 "七分",
 "假",
 "三分",
 "真",
 "也",
 "够",
 "我",
 "共",
 "你",
 "一次",
 "又",
 "一次",
 "热吻",
 "真",
 "天真",
 "假",
 "天真",
 "我",
 "怕",
 "我",
 "忘",
 "了",
 "怎么",
 "区分",
 "七分",
 "假",
 "三分",
 "真",
 "也",
 "够",
 "我",
 "共",
 "你",
 "一次",
 "又",
 "一次",
 "热吻",
 "真",
 "天真",
 "假",
 "天真",
 "我",
 "怕",
 "我",
 "忘",
 "了",
 "怎么",
 "区分",
 "七分",
 "假",
 "三分",
 "真",
 "也",
 "够",
 "我",
 "共",
 "你",
 "一次",
 "又",
 "一次",
 "热吻"]}