{"artist_name": "杨宗纬",
 "song_name": "低回",
 "song_id": "26075547",
 "song_lyric": "作曲 : 鸦片丹\n 作词 : 杨宗纬\n只有沉默\xa0才能听懂沉默\n只有想念\xa0才用想念包裹\n只有胸怀里的痛\n才会在胸怀里淹没\n只有安静\xa0特别赤裸\n独自绕过\xa0回忆埋伏的巷弄\n什么时候\xa0换你埋伏在街口\n你总爱装懂地说\n生命有时天晴有时胶着\n说完后不久\xa0你撒手就走\xa0如此洒脱\n我们还没走过那撒哈拉沙漠\n也没有在亚马逊雨林探险过\n冰岛搭帐篷\xa0黄河里游泳\n都没有过\xa0只有彼此允诺\n你说过\xa0要去那肯尼亚坐热气球\n牵着手\xa0漫步在爱琴海的日落\n到底有没有\xa0为什么不开口\n还是要我\xa0相信你已\xa0挥手\xa0告别了\n\n独自绕过\xa0回忆埋伏的巷弄\n什么时候\xa0换你埋伏在街口\n你总爱装懂地说\n生命有时天晴有时胶着\n说完后不久\xa0你撒手就走\xa0如此洒脱\n我们还没走过那撒哈拉沙漠\n也没有在亚马逊雨林探险过\n冰岛搭帐篷\xa0黄河里游泳\n都没有过\xa0只有彼此允诺\n你说过\xa0要去那肯尼亚坐热气球\n牵着手\xa0漫步在爱琴海的日落\n到底有没有\xa0为什么不开口\n还是要我\xa0相信你已\xa0挥手\xa0告别了\n\n那一天挂着笑\xa0来到我的面前\n这一刻挂着笑\xa0却从此闭上眼\n什么叫永远\xa0你惭不惭愧\n现在我\xa0只有思念作陪\n整个夜\xa0剩下一片寂寞在旋飞\n我的泪\xa0一颗颗堆在你的信笺\n有你的世界\xa0慢慢在支解\n剩你的话\xa0彷佛絮语\n喃喃地\xa0低回",
 "pic_url": "http://p1.music.126.net/LvDBXsBEuGK-ZNVs3XmRVg==/7926379325753599.jpg",
 "words": ["作曲",
 "鸦片",
 "丹",
 "作词",
 "杨",
 "宗",
 "纬",
 "只有",
 "沉默",
 "才能",
 "听懂",
 "沉默",
 "只有",
 "想念",
 "才",
 "用",
 "想念",
 "包裹",
 "只有",
 "胸怀",
 "怀里",
 "的",
 "痛",
 "才",
 "会",
 "在",
 "胸怀",
 "怀里",
 "淹没",
 "只有",
 "安静",
 "特别",
 "赤裸",
 "独自",
 "绕过",
 "回忆",
 "埋伏",
 "的",
 "巷弄",
 "什么",
 "时候",
 "换",
 "你",
 "埋伏",
 "在",
 "街口",
 "你",
 "总",
 "爱",
 "装懂",
 "地",
 "说",
 "生命",
 "有时",
 "天晴",
 "有时",
 "胶着",
 "说完",
 "后",
 "不久",
 "你",
 "撒手",
 "就",
 "走",
 "如此",
 "洒脱",
 "我们",
 "还",
 "没",
 "走过",
 "那",
 "撒哈拉",
 "撒哈拉沙漠",
 "哈拉",
 "沙漠",
 "也",
 "没有",
 "在",
 "亚马",
 "亚马逊",
 "雨林",
 "探险",
 "过",
 "冰岛",
 "搭帐篷",
 "帐篷",
 "黄河",
 "河里",
 "游泳",
 "都",
 "没有",
 "过",
 "只有",
 "彼此",
 "允诺",
 "你",
 "说",
 "过",
 "要",
 "去",
 "那",
 "肯尼",
 "肯尼亚",
 "尼亚",
 "坐",
 "热气",
 "热气球",
 "气球",
 "牵着手",
 "着手",
 "漫步",
 "在",
 "爱琴",
 "爱琴海",
 "的",
 "日落",
 "到底",
 "有没有",
 "没有",
 "为什么",
 "什么",
 "不开",
 "开口",
 "还是",
 "要",
 "我",
 "相信",
 "你",
 "已",
 "挥手",
 "告别",
 "了",
 "独自",
 "绕过",
 "回忆",
 "埋伏",
 "的",
 "巷弄",
 "什么",
 "时候",
 "换",
 "你",
 "埋伏",
 "在",
 "街口",
 "你",
 "总",
 "爱",
 "装懂",
 "地",
 "说",
 "生命",
 "有时",
 "天晴",
 "有时",
 "胶着",
 "说完",
 "后",
 "不久",
 "你",
 "撒手",
 "就",
 "走",
 "如此",
 "洒脱",
 "我们",
 "还",
 "没",
 "走过",
 "那",
 "撒哈拉",
 "撒哈拉沙漠",
 "哈拉",
 "沙漠",
 "也",
 "没有",
 "在",
 "亚马",
 "亚马逊",
 "雨林",
 "探险",
 "过",
 "冰岛",
 "搭帐篷",
 "帐篷",
 "黄河",
 "河里",
 "游泳",
 "都",
 "没有",
 "过",
 "只有",
 "彼此",
 "允诺",
 "你",
 "说",
 "过",
 "要",
 "去",
 "那",
 "肯尼",
 "肯尼亚",
 "尼亚",
 "坐",
 "热气",
 "热气球",
 "气球",
 "牵着手",
 "着手",
 "漫步",
 "在",
 "爱琴",
 "爱琴海",
 "的",
 "日落",
 "到底",
 "有没有",
 "没有",
 "为什么",
 "什么",
 "不开",
 "开口",
 "还是",
 "要",
 "我",
 "相信",
 "你",
 "已",
 "挥手",
 "告别",
 "了",
 "那",
 "一天",
 "挂",
 "着",
 "笑",
 "来到",
 "我",
 "的",
 "面前",
 "这",
 "一刻",
 "挂",
 "着",
 "笑",
 "却",
 "从此",
 "闭上眼",
 "上眼",
 "什么",
 "叫",
 "永远",
 "你",
 "惭",
 "不",
 "惭愧",
 "现在",
 "我",
 "只有",
 "思念",
 "念作",
 "作陪",
 "整个",
 "夜",
 "剩下",
 "一片",
 "寂寞",
 "在",
 "旋",
 "飞",
 "我",
 "的",
 "泪",
 "一颗",
 "一颗颗",
 "堆",
 "在",
 "你",
 "的",
 "信笺",
 "有",
 "你",
 "的",
 "世界",
 "慢慢",
 "在",
 "支解",
 "剩",
 "你",
 "的话",
 "彷佛",
 "絮语",
 "喃喃",
 "喃喃地",
 "低回"]}