{"artist_name": "梁心颐",
 "song_name": "当秋天遇上秋天",
 "song_id": "273794",
 "song_lyric": "一样趴在床头写日记\n一样准时喂饱你的鱼\n一样很想你 真的很想你\n每一天收到你的信才有好心情\n\n习惯了一个人回家\n一个人shopping\n一个人看电影\n从二月的花开到秋天看海\n一路上你不在\n\n亲爱的我没有责怪\n只是不明白\n你是如何相信未来\n若我对你不再有依赖\n我的自在 你还爱不爱\n\n一样忙到忘了星期几\n一样搭最晚的MRT\n一样很想你 真的很想你\n但最近总没有时间回复你的信\n\n你也是一个人睡吗\n一个人旅行\n一个人看星星\n今年的圣诞夜到了情人节\n是谁在你身边\n\n亲爱的我没有责怪\n只是不明白\n爱该不该互相等待\n若你对我不再有依赖\n你的自在 我还爱不爱\n\n亲爱的今年的秋天\n分外的收敛\n没有纷飞的落叶\n如同我们分开\n回忆停摆 感情少了精彩\n\n亲爱的我没有责怪\n只是渐渐明白\n恋爱无法只有等待\n当秋天又遇上了秋天\n随这枫叶我也会放开\n当秋天遇上秋天\n当秋天遇上秋天\n你不在身边",
 "pic_url": "http://p1.music.126.net/FwYrdj5tnTWk8aUlaTMkZg==/59373627915535.jpg",
 "words": ["一样",
 "趴在",
 "床头",
 "写日记",
 "日记",
 "一样",
 "准时",
 "喂饱",
 "你",
 "的",
 "鱼",
 "一样",
 "很",
 "想",
 "你",
 "真的",
 "很",
 "想",
 "你",
 "每",
 "一天",
 "收到",
 "你",
 "的",
 "信",
 "才",
 "有",
 "好心",
 "心情",
 "习惯",
 "了",
 "一个",
 "个人",
 "回家",
 "一个",
 "个人",
 "一个",
 "个人",
 "看",
 "电影",
 "从",
 "二月",
 "的",
 "花开",
 "开到",
 "秋天",
 "看",
 "海",
 "一路",
 "一路上",
 "路上",
 "你",
 "不在",
 "亲爱",
 "的",
 "我",
 "没有",
 "有责",
 "责怪",
 "只是",
 "不明",
 "明白",
 "你",
 "是",
 "如何",
 "相信",
 "未来",
 "若",
 "我",
 "对",
 "你",
 "不再",
 "再有",
 "依赖",
 "我",
 "的",
 "自在",
 "你",
 "还",
 "爱不爱",
 "一样",
 "忙",
 "到",
 "忘",
 "了",
 "星期",
 "几",
 "一样",
 "搭",
 "最晚",
 "的",
 "一样",
 "很",
 "想",
 "你",
 "真的",
 "很",
 "想",
 "你",
 "但",
 "最近",
 "总",
 "没有",
 "有时",
 "时间",
 "回复",
 "你",
 "的",
 "信",
 "你",
 "也",
 "是",
 "一个",
 "个人",
 "睡",
 "吗",
 "一个",
 "个人",
 "旅行",
 "一个",
 "个人",
 "看",
 "星星",
 "今年",
 "的",
 "圣诞",
 "圣诞夜",
 "到",
 "了",
 "情人",
 "情人节",
 "是",
 "谁",
 "在",
 "你",
 "身边",
 "亲爱",
 "的",
 "我",
 "没有",
 "有责",
 "责怪",
 "只是",
 "不明",
 "明白",
 "爱",
 "该不该",
 "不该",
 "互相",
 "相等",
 "等待",
 "若",
 "你",
 "对",
 "我",
 "不再",
 "再有",
 "依赖",
 "你",
 "的",
 "自在",
 "我",
 "还",
 "爱不爱",
 "亲爱",
 "的",
 "今年",
 "的",
 "秋天",
 "分外",
 "的",
 "收敛",
 "没有",
 "纷飞",
 "的",
 "落叶",
 "如同",
 "我们",
 "分开",
 "回忆",
 "停摆",
 "感情",
 "少",
 "了",
 "精彩",
 "亲爱",
 "的",
 "我",
 "没有",
 "有责",
 "责怪",
 "只是",
 "渐渐",
 "明白",
 "恋爱",
 "无法",
 "只有",
 "等待",
 "当",
 "秋天",
 "又",
 "遇上",
 "了",
 "秋天",
 "随",
 "这",
 "枫叶",
 "我",
 "也",
 "会",
 "放开",
 "当",
 "秋天",
 "遇上",
 "秋天",
 "当",
 "秋天",
 "遇上",
 "秋天",
 "你",
 "不在",
 "身边"]}