{"artist_name": "梁心颐",
 "song_name": "Darling",
 "song_id": "273790",
 "song_lyric": "白色谎言遮住了蓝天的笑脸\n藏在乌云后的真心模糊一片\n倾盆大雨 浇醒了我清晰了\n爱你的念头\n镜子却反射双面情人的负重\n\n没有了光环 不再伪装 能否爱我如从前 那模样\nDarling这次 我要更诚实的 爱你\n抛开面具 彻底面对自己\nDarling 我素颜才是爱情的美丽\n这次我的心为你 透明\n\n褪去纯真保护色比想象中难\n说不出口的 脆弱 不想再隐瞒\n我需要你 就像阳光 划过去阴霾全照亮\n\n坦承是我们的桥梁 不再疯狂\n相信Darling这次 我要更诚实的 爱你\n抛开面具 彻底面对自己\nDarling 我素颜才是是爱情的美丽\n这次我的心为你 透明\nDarling这次 我要更诚实的 爱你\n抛开面具 彻底面对自己\n\n\nDarling 我素颜才是爱情的美丽\n这次我的心为你 透明\n\noH~ Darling这次 我要更诚实的 爱你\n抛开面具 彻底面对自己\nDarling 我素颜才是爱情的美丽\n就算历程在艰辛 每秒我都珍惜\n\n飞往自由蓝天 飞奔回你身边\n风速给我勇气向前\n\n为爱你而改变 也是爱自己的起点",
 "pic_url": "http://p1.music.126.net/dN0C6lYbbQCjY57K3xJ2og==/48378511638148.jpg",
 "words": ["白色",
 "谎言",
 "遮住",
 "了",
 "蓝天",
 "的",
 "笑脸",
 "藏",
 "在",
 "乌云",
 "后",
 "的",
 "真心",
 "模糊",
 "一片",
 "倾盆",
 "倾盆大雨",
 "大雨",
 "浇",
 "醒",
 "了",
 "我",
 "清晰",
 "了",
 "爱",
 "你",
 "的",
 "念头",
 "镜子",
 "却",
 "反射",
 "双面",
 "情人",
 "的",
 "负重",
 "没有",
 "了",
 "光环",
 "不再",
 "伪装",
 "能否",
 "爱",
 "我",
 "如",
 "从前",
 "那",
 "模样",
 "这次",
 "我",
 "要",
 "更",
 "诚实",
 "的",
 "爱",
 "你",
 "抛开",
 "面具",
 "彻底",
 "底面",
 "面对",
 "自己",
 "我",
 "素",
 "颜",
 "才",
 "是",
 "爱情",
 "的",
 "美丽",
 "这次",
 "我",
 "的",
 "心",
 "为",
 "你",
 "透明",
 "褪去",
 "纯真",
 "保护",
 "保护色",
 "比",
 "想象",
 "中",
 "难",
 "说不出",
 "说不出口",
 "不出",
 "出口",
 "的",
 "脆弱",
 "不想",
 "再",
 "隐瞒",
 "我",
 "需要",
 "你",
 "就",
 "像",
 "阳光",
 "划过",
 "划过去",
 "过去",
 "阴霾",
 "全",
 "照亮",
 "坦承",
 "是",
 "我们",
 "的",
 "桥梁",
 "不再",
 "疯狂",
 "相信",
 "Darling",
 "这次",
 "我",
 "要",
 "更",
 "诚实",
 "的",
 "爱",
 "你",
 "抛开",
 "面具",
 "彻底",
 "底面",
 "面对",
 "自己",
 "我",
 "素",
 "颜",
 "才",
 "是",
 "是",
 "爱情",
 "的",
 "美丽",
 "这次",
 "我",
 "的",
 "心",
 "为",
 "你",
 "透明",
 "这次",
 "我",
 "要",
 "更",
 "诚实",
 "的",
 "爱",
 "你",
 "抛开",
 "面具",
 "彻底",
 "底面",
 "面对",
 "自己",
 "我",
 "素",
 "颜",
 "才",
 "是",
 "爱情",
 "的",
 "美丽",
 "这次",
 "我",
 "的",
 "心",
 "为",
 "你",
 "透明",
 "Darling",
 "这次",
 "我",
 "要",
 "更",
 "诚实",
 "的",
 "爱",
 "你",
 "抛开",
 "面具",
 "彻底",
 "底面",
 "面对",
 "自己",
 "我",
 "素",
 "颜",
 "才",
 "是",
 "爱情",
 "的",
 "美丽",
 "就算",
 "历程",
 "在",
 "艰辛",
 "每秒",
 "我",
 "都",
 "珍惜",
 "飞往",
 "自由",
 "蓝天",
 "飞奔",
 "奔回",
 "你",
 "身边",
 "风速",
 "给",
 "我",
 "勇气",
 "向前",
 "为",
 "爱",
 "你",
 "而",
 "改变",
 "也",
 "是",
 "爱",
 "自己",
 "的",
 "起点"]}