{"artist_name": "李佳薇",
"song_name": "如果爱是星光",
"song_id": "274704",
"song_lyric":
 "作曲 : 管启源\n 作词 : 李偲菘\n看着电视节目\t有人在痛哭\n关于爱情追逐\t总是那么感人肺腑\n同样故事一直重复\n\n生活朋友啤酒\t偶而有点苦\n心情上下起伏\t并不怕这一点孤独\n谁又想当柔弱的公主\n\n梦想并没有说明书\t靠直觉建筑\n爱没有地图\t凭勇气找路\n幸福不幸福\n每个人都有另一个人照顾\tYeah\n我只有一个小衣橱\t一个人居住\n寂寞的围堵\t我可以克服\n幸福不幸福\t不是定义人生的唯一指数\nCome\ton\tLet's\tGo\n生活就像小铜板\t坏的好的轮流转\n如果爱是星光\t让我发着光\n伤口都是小徽章\t记念了我的坚强\n口袋藏着阳光\t天气好晴朗\n看着电视节目\t有人在痛哭\n关于爱情追逐\t总是那么感人肺腑\n同样故事一直重复\n\n生活朋友啤酒\t偶而有点苦\n心情上下起伏\t并不怕这一点孤独\n谁又想当柔弱的公主\n\n梦想并没有说明书\t靠直觉建筑\n爱没有地图\t凭勇气找路\n幸福不幸福\n每个人都有另一个人照顾\tYeah\n我只有一个小衣橱\t一个人居住\n寂寞的围堵\t我可以克服\n幸福不幸福\t不是定义人生的唯一指数\nCome\ton\tLet's\tGo\n生活就像小铜板\t坏的好的轮流转\n如果爱是星光\t让我发着光\n伤口都是小徽章\t记念了我的坚强\n口袋藏着阳光\t天气好晴朗",
"pic_url": "http://p1.music.126.net/6VshvgnaD5VBs_z4j1QKlA==/109951163188719203.jpg",
"words": ["作曲", "管", "启", "源", "作词", "李", "偲", "菘", "看着", "电视", "电视节", "电视节目", "节目", "有人", "在", "痛哭", "关于", "爱情", "追逐", "总是", "那么", "感人", "感人肺腑", "肺腑", "同样", "故事", "一直", "重复", "生活", "朋友", "啤酒", "偶而", "而有", "有点", "苦", "心情", "上下", "下起", "起伏", "并", "不怕", "这", "一点", "孤独", "谁", "又", "想", "当", "柔弱", "的", "公主", "梦想", "并", "没有", "说明", "说明书", "靠", "直觉", "建筑", "爱", "没有", "地图", "凭", "勇气", "找", "路", "幸福", "不幸", "幸福", "每个", "个人", "都", "有", "另", "一个", "个人", "照顾", "我", "只有", "一个", "小", "衣橱", "一个", "个人", "人居", "居住", "寂寞", "的", "围堵", "我", "可以", "克服", "幸福", "不幸", "幸福", "不是", "定义", "人生", "的", "唯一", "指数", "on", "Let", "s", "生活", "就", "像", "小", "铜板", "坏", "的", "好", "的", "轮流", "轮流转", "流转", "如果", "爱", "是", "星光", "让", "我", "发着", "光", "伤口", "都", "是", "小", "徽章", "记念", "了", "我", "的", "坚强", "口袋", "藏", "着", "阳光", "天气", "好", "晴朗", "看着", "电视", "电视节", "电视节目", "节目", "有人", "在", "痛哭", "关于", "爱情", "追逐", "总是", "那么", "感人", "感人肺腑", "肺腑", "同样", "故事", "一直", "重复", "生活", "朋友", "啤酒", "偶而", "而有", "有点", "苦", "心情", "上下", "下起", "起伏", "并", "不怕", "这", "一点", "孤独", "谁", "又", "想", "当", "柔弱", "的", "公主", "梦想", "并", "没有", "说明", "说明书", "靠", "直觉", "建筑", "爱", "没有", "地图", "凭", "勇气", "找", "路", "幸福", "不幸", "幸福", "每个", "个人", "都", "有", "另", "一个", "个人", "照顾", "我", "只有", "一个", "小", "衣橱", "一个", "个人", "人居", "居住", "寂寞", "的", "围堵", "我", "可以", "克服", "幸福", "不幸", "幸福", "不是", "定义", "人生", "的", "唯一", "指数", "on", "Let", "s", "生活", "就", "像", "小", "铜板", "坏", "的", "好", "的", "轮流", "轮流转", "流转", "如果", "爱", "是", "星光", "让", "我", "发着", "光", "伤口", "都", "是", "小", "徽章", "记念", "了", "我", "的", "坚强", "口袋", "藏", "着", "阳光", "天气", "好", "晴朗"]}