{"artist_name": "Hush!",
 "song_name": "集体催眠",
 "song_id": "27598480",
 "song_lyric": "散布所有具毁灭能力的联想\n卸除防卫的心再筑起一道墙\n墙的张贴是爬满暗示性的文章\n“培养子孙的家”\n\n装了情感的枪做合理的犯法\n瞄准空洞的信仰温柔地开枪\n上了颜色的疤是枪口说的神话\n“迎接高塔倒塌”\n\n承认吧 历史的所言不假\n指引的光芒 是集体催眠的假象\n看穿它 学习夜鹰的眼光\n凝视它 猎捕它\n\n装了情感的枪做合理的犯法\n瞄准空洞的信仰温柔地开枪\n上了颜色的疤是枪口说的神话\n“迎接高塔倒塌”\n\n承认吧 历史的所言不假\n指引的光芒 是集体催眠的假象\n看穿它 学习夜鹰的眼光\n凝视它 猎捕它",
 "pic_url": "http://p1.music.126.net/6LdS-QfFPbwCJsRyO-r2xw==/3142404232262770.jpg",
 "words": ["散布",
 "所有",
 "具",
 "毁灭",
 "能力",
 "的",
 "联想",
 "卸除",
 "防卫",
 "的",
 "心",
 "再",
 "筑起",
 "一道",
 "墙",
 "墙",
 "的",
 "张贴",
 "是",
 "爬满",
 "暗示",
 "暗示性",
 "示性",
 "的",
 "文章",
 "培养",
 "养子",
 "子孙",
 "的",
 "家",
 "装",
 "了",
 "情感",
 "的",
 "枪",
 "做",
 "合理",
 "的",
 "犯法",
 "瞄准",
 "空洞",
 "的",
 "信仰",
 "温柔",
 "地",
 "开枪",
 "上",
 "了",
 "颜色",
 "的",
 "疤",
 "是",
 "枪口",
 "口说",
 "的",
 "神话",
 "迎接",
 "高塔",
 "倒塌",
 "承认",
 "吧",
 "历史",
 "的",
 "所言",
 "不",
 "假",
 "指引",
 "的",
 "光芒",
 "是",
 "集体",
 "催眠",
 "的",
 "假象",
 "看穿",
 "它",
 "学习",
 "夜鹰",
 "的",
 "眼光",
 "凝视",
 "它",
 "猎捕",
 "它",
 "装",
 "了",
 "情感",
 "的",
 "枪",
 "做",
 "合理",
 "的",
 "犯法",
 "瞄准",
 "空洞",
 "的",
 "信仰",
 "温柔",
 "地",
 "开枪",
 "上",
 "了",
 "颜色",
 "的",
 "疤",
 "是",
 "枪口",
 "口说",
 "的",
 "神话",
 "迎接",
 "高塔",
 "倒塌",
 "承认",
 "吧",
 "历史",
 "的",
 "所言",
 "不",
 "假",
 "指引",
 "的",
 "光芒",
 "是",
 "集体",
 "催眠",
 "的",
 "假象",
 "看穿",
 "它",
 "学习",
 "夜鹰",
 "的",
 "眼光",
 "凝视",
 "它",
 "猎捕",
 "它"]}