{"artist_name": "梅艳芳",
"song_name": "夏娃，夏娃",
"song_id": "276263",
"song_lyric":
 "梅:和谁眉毛\n琳:同样的弯\n梅:和谁皮鞋\n琳:同样的高\n梅:和谁望着\n琳:同样的天\n梅:和谁才能\n琳:互相将化妆卸下\n梅:然后赤裸对话\n琳:是姊是妹\n梅:是爱吧\n琳:题目太大\n合:就算天国没有亚当\n琳:有两个夏娃\n梅:除下我的耳环\n琳:垂在我的耳下\n合:陪着别人做到吗\n梅:瞳孔闪得多么好\n琳:什么深刻睇不到\n梅:同样天生这么好\n琳:但他怎么知道\n梅:是你先会知道\n合:爱得好 吻得好 明白我的构造\n梅:唇彩湿得多么好\n琳:什么心思讲不到\n梅:同穿婚纱好不好\n琳:但他只想拥抱\n梅:而女人要心到\n合:要多好 有多好 还是女人够酷\n梅:梦露梦断\n琳:黛玉捧心\n梅:任白长全\n琳:梁祝牺牲\n梅:和谁才能\n琳:同样真心\n梅:和谁才能\n琳:互相都觉得灿烂\n梅:容纳我不灿烂\n琳:是姊是妹\n梅:是爱吧\n琳:题目太大\n梅:就算天国没有亚当\n琳:有两个夏娃\n梅:拿着我的发蜡\n琳:潜入我的发下\n合:陪着别人做到吗\n梅:瞳孔闪得多么好\n琳:什么深刻睇不到\n梅:同样天生这么好\n琳:但他怎么知道\n梅:是你先会知道\n合:爱得好 吻得好 明白我的构造\n梅:唇彩湿得多么好\n琳:什么心思讲不到\n梅:同穿婚纱好不好\n琳:但他只想拥抱\n梅:而女人要心到\n合:要多好 有多好 还是女人够酷\n梅:瞳孔闪得多么好\n琳:什么深刻睇不到\n梅:同样天生这么好\n琳:但他怎么知道\n梅:是你先会知道\n合:爱得好 吻得好 明白我的构造\n梅:唇彩湿得多么好\n琳:什么心思讲不到\n梅:同穿婚纱好不好\n琳:但他只想拥抱\n梅:而女人要心到\n合:要多好 有多好 还是女人够酷\n合:我多好 你多好 还是女人够酷",
"pic_url": "http://p1.music.126.net/0MAPTbgbHUjwSTMCptrC8A==/19058934556163936.jpg",
"words": ["梅", "和", "谁", "眉毛", "琳", "同样", "的", "弯", "梅", "和", "谁", "皮鞋", "琳", "同样", "的", "高", "梅", "和", "谁", "望", "着", "琳", "同样", "的", "天", "梅", "和", "谁", "才能", "琳", "互相", "将", "化妆", "卸下", "梅", "然后", "赤裸", "对话", "琳", "是", "姊", "是", "妹", "梅", "是", "爱", "吧", "琳", "题目", "太大", "合", "就算", "天国", "没有", "亚当", "琳", "有", "两个", "夏娃", "梅", "除", "下", "我", "的", "耳环", "琳", "垂", "在", "我", "的", "耳", "下", "合", "陪", "着", "别人", "做到", "吗", "梅", "瞳孔", "闪", "得", "多么", "好", "琳", "什么", "深刻", "睇", "不到", "梅", "同样", "天生", "这么", "好", "琳", "但", "他", "怎么", "知道", "梅", "是", "你", "先会", "知道", "合", "爱", "得", "好", "吻", "得", "好", "明白", "我", "的", "构造", "梅", "唇彩", "湿", "得", "多么", "好", "琳", "什么", "心思", "讲", "不到", "梅", "同", "穿", "婚纱", "好不好", "不好", "琳", "但", "他", "只", "想", "拥抱", "梅", "而", "女人", "要", "心", "到", "合", "要", "多", "好", "有", "多", "好", "还是", "女人", "够", "酷", "梅", "梦露", "梦", "断", "琳", "黛", "玉", "捧心", "梅", "任", "白", "长", "全", "琳", "梁祝", "牺牲", "梅", "和", "谁", "才能", "琳", "同样", "真心", "梅", "和", "谁", "才能", "琳", "互相", "都", "觉得", "灿烂", "梅", "容纳", "我", "不", "灿烂", "琳", "是", "姊", "是", "妹", "梅", "是", "爱", "吧", "琳", "题目", "太大", "梅", "就算", "天国", "没有", "亚当", "琳", "有", "两个", "夏娃", "梅", "拿", "着", "我", "的", "发蜡", "琳", "潜入", "我", "的", "发下", "合", "陪", "着", "别人", "做到", "吗", "梅", "瞳孔", "闪", "得", "多么", "好", "琳", "什么", "深刻", "睇", "不到", "梅", "同样", "天生", "这么", "好", "琳", "但", "他", "怎么", "知道", "梅", "是", "你", "先会", "知道", "合", "爱", "得", "好", "吻", "得", "好", "明白", "我", "的", "构造", "梅", "唇彩", "湿", "得", "多么", "好", "琳", "什么", "心思", "讲", "不到", "梅", "同", "穿", "婚纱", "好不好", "不好", "琳", "但", "他", "只", "想", "拥抱", "梅", "而", "女人", "要", "心", "到", "合", "要", "多", "好", "有", "多", "好", "还是", "女人", "够", "酷", "梅", "瞳孔", "闪", "得", "多么", "好", "琳", "什么", "深刻", "睇", "不到", "梅", "同样", "天生", "这么", "好", "琳", "但", "他", "怎么", "知道", "梅", "是", "你", "先会", "知道", "合", "爱", "得", "好", "吻", "得", "好", "明白", "我", "的", "构造", "梅", "唇彩", "湿", "得", "多么", "好", "琳", "什么", "心思", "讲", "不到", "梅", "同", "穿", "婚纱", "好不好", "不好", "琳", "但", "他", "只", "想", "拥抱", "梅", "而", "女人", "要", "心", "到", "合", "要", "多", "好", "有", "多", "好", "还是", "女人", "够", "酷", "合", "我", "多", "好", "你", "多", "好", "还是", "女人", "够", "酷"]}