{"artist_name": "卢巧音",
"song_name": "色与情",
"song_id": "28636047",
"song_lyric":
 "城中不似天堂 颜色偏太多\n谁只需要苍白 衣装\n悉心装扮 不要沮丧\n咩一个背囊 想装到风光\n营造我色相\n我怕你看到我脆弱\n我要你看到我漂亮 经过\n留下我色相\n哪个会对我有印象\n哪个会知我晚上 难过\n城中一齐匆忙 回忆不太多\n或者只有新颖 衣装\n悉心装扮 偏更沮丧\n穿一对皮鞋 想追到康庄\n营造我色相\n我怕你看到我脆弱\n我要你看到我漂亮 经过\n留下我色相\n哪个会对我有印象\n哪个会知我晚上 难过\nah.... ah.... ah....... ah.....\n一觉醒过想变色\n变换我外衣的衬色\n但城外仍旧 挤逼\n营造我色相\n我怕你看到我脆弱\n我要你看到我漂亮 经过\n留下我色相\n哪个会对我有印象\n哪个会知我晚上 难过\n谁亦爱色相\n这世界怕看我脆弱\n这世界爱看我漂亮 经过\n留下我色相\n那个也看见我这样\n那个要知我那样 情况..",
"pic_url": "http://p1.music.126.net/BWwaWRnpK7tiJhuKWHUrtQ==/109951163032569250.jpg",
"words": ["城中", "不似", "天堂", "颜色", "偏", "太多", "谁", "只", "需要", "苍白", "衣装", "悉心", "装扮", "不要", "沮丧", "咩", "一个", "背囊", "想装", "装到", "风光", "营造", "我", "色相", "我", "怕", "你", "看到", "我", "脆弱", "我", "要", "你", "看到", "我", "漂亮", "经过", "留下", "我", "色相", "哪个", "会", "对", "我", "有", "印象", "哪个", "会", "知", "我", "晚上", "难过", "城中", "一齐", "匆忙", "回忆", "不", "太多", "或者", "只有", "新颖", "衣装", "悉心", "装扮", "偏", "更", "沮丧", "穿", "一对", "皮鞋", "想", "追到", "康庄", "营造", "我", "色相", "我", "怕", "你", "看到", "我", "脆弱", "我", "要", "你", "看到", "我", "漂亮", "经过", "留下", "我", "色相", "哪个", "会", "对", "我", "有", "印象", "哪个", "会", "知", "我", "晚上", "难过", "ah", "ah", "ah", "一觉", "觉醒", "过", "想变", "变色", "变换", "我", "外衣", "的", "衬", "色", "但", "城外", "仍旧", "挤逼", "营造", "我", "色相", "我", "怕", "你", "看到", "我", "脆弱", "我", "要", "你", "看到", "我", "漂亮", "经过", "留下", "我", "色相", "哪个", "会", "对", "我", "有", "印象", "哪个", "会", "知", "我", "晚上", "难过", "谁", "亦", "爱", "色相", "这", "世界", "怕", "看", "我", "脆弱", "这", "世界", "爱看", "我", "漂亮", "经过", "留下", "我", "色相", "那个", "也", "看见", "我", "这样", "那个", "要", "知", "我", "那样", "情况"]}