{"artist_name": "张智霖",
 "song_name": "绝世绝招",
 "song_id": "28853351",
 "song_lyric": "男 : 啊 ……   啊……    啊……\n女 : 啊 ……   啊……    啊……\n合 : 抬 头 望 望 向 青 天 美 景\n男 ：绝 世 绝 招 绝 顶\n女 ：情 倾 人 倾 心 倾\n男 ：仰 天 一 笑 望 穹 苍 问 句\n合 ：究 竟 世 上 什 麽 最 劲\n男 ：射 雕 射 狮 射 虎\n女 ：留 英 雄 身 影\n男 ：仰 天 一 笑 望 乾 坤 问 句\n合 ：最 高 最 极 限 是 谁 定\n合 ：人 间 好 汉\n   豪 情 壮 志  红 尘 精 英\n合 ：倾 我 自 发 自 创 的 冲 劲\n写 我 的 经\n 自 我 发 光 发 声 云 上 抱 月 抱 星\n 愿 共 青 天 一 试 心 中 焯 热 情\nTVB94射雕英雄传主题曲 : 绝 世 绝 招\n合 ：人 间 好 汉\n   豪 情 壮 志  红 尘 精 英\n合 ：倾 我 自 发 自 创 的 冲 劲\n写 我 的 经\n 自 我 发 光 发 声 云 上 抱 月 抱 星\n 愿 共 青 天 一 试 心 中 焯 热 情\n男 ：射 雕 射 狮 射 虎\n女 ：留 英 雄 身 影\n男 ：要 此 生 此 世 任 人 生 而 决\n合 ：至 高 极 限 自 来 定",
 "pic_url": "http://p1.music.126.net/JotrymTxxInYarQdqU_Y1w==/6000034953325977.jpg",
 "words": ["男",
 "啊",
 "啊",
 "啊",
 "女",
 "啊",
 "啊",
 "啊",
 "合",
 "抬",
 "头",
 "望",
 "望",
 "向",
 "青",
 "天",
 "美",
 "景",
 "男",
 "绝",
 "世",
 "绝",
 "招",
 "绝",
 "顶",
 "女",
 "情",
 "倾",
 "人",
 "倾",
 "心",
 "倾",
 "男",
 "仰",
 "天",
 "一",
 "笑",
 "望",
 "穹",
 "苍",
 "问",
 "句",
 "合",
 "究",
 "竟",
 "世",
 "上",
 "什",
 "麽",
 "最",
 "劲",
 "男",
 "射",
 "雕",
 "射",
 "狮",
 "射",
 "虎",
 "女",
 "留",
 "英",
 "雄",
 "身",
 "影",
 "男",
 "仰",
 "天",
 "一",
 "笑",
 "望",
 "乾",
 "坤",
 "问",
 "句",
 "合",
 "最",
 "高",
 "最",
 "极",
 "限",
 "是",
 "谁",
 "定",
 "合",
 "人",
 "间",
 "好",
 "汉",
 "豪",
 "情",
 "壮",
 "志",
 "红",
 "尘",
 "精",
 "英",
 "合",
 "倾",
 "我",
 "自",
 "发",
 "自",
 "创",
 "的",
 "冲",
 "劲",
 "写",
 "我",
 "的",
 "经",
 "自",
 "我",
 "发",
 "光",
 "发",
 "声",
 "云",
 "上",
 "抱",
 "月",
 "抱",
 "星",
 "愿",
 "共",
 "青",
 "天",
 "一",
 "试",
 "心",
 "中",
 "焯",
 "热",
 "情",
 "射雕",
 "英雄",
 "英雄传",
 "传主",
 "主题",
 "主题曲",
 "绝",
 "世",
 "绝",
 "招",
 "合",
 "人",
 "间",
 "好",
 "汉",
 "豪",
 "情",
 "壮",
 "志",
 "红",
 "尘",
 "精",
 "英",
 "合",
 "倾",
 "我",
 "自",
 "发",
 "自",
 "创",
 "的",
 "冲",
 "劲",
 "写",
 "我",
 "的",
 "经",
 "自",
 "我",
 "发",
 "光",
 "发",
 "声",
 "云",
 "上",
 "抱",
 "月",
 "抱",
 "星",
 "愿",
 "共",
 "青",
 "天",
 "一",
 "试",
 "心",
 "中",
 "焯",
 "热",
 "情",
 "男",
 "射",
 "雕",
 "射",
 "狮",
 "射",
 "虎",
 "女",
 "留",
 "英",
 "雄",
 "身",
 "影",
 "男",
 "要",
 "此",
 "生",
 "此",
 "世",
 "任",
 "人",
 "生",
 "而",
 "决",
 "合",
 "至",
 "高",
 "极",
 "限",
 "自",
 "来",
 "定"]}