{"artist_name": "布衣乐队",
 "song_name": "小花",
 "song_id": "28860658",
 "song_lyric": "啦......\n啦......\n 作曲 : 吴宁越\n 作词 : 吴宁越\n走过风路过的地方\n回头看来的方向\n向着太阳的小花\n冲你笑 冲我笑\n百合花开了\n野菊花也盛开了\n散发着新的味道\n等你来 等你来\n酒已开始在流淌\n流向醉人的地方\n依稀看见你的样子\n在前方 在远方\n歌声已经走了\n走到听不见的地方\n是否能像花儿一样\n还会开 还会开\n啦啦\n歌声已经走了\n走到听不见的地方\n是否能像花儿一样\n还会开 还会开\n还会开\n还会开\n梦",
 "pic_url": "http://p1.music.126.net/-9YWFBfzCRCuAcIN-aJlsQ==/8895049068708076.jpg",
 "words": ["啦",
 "啦",
 "作曲",
 "吴",
 "宁",
 "越",
 "作词",
 "吴",
 "宁",
 "越",
 "走过",
 "风",
 "路过",
 "的",
 "地方",
 "回头",
 "看来",
 "的",
 "方向",
 "向着",
 "太阳",
 "的",
 "小花",
 "冲",
 "你",
 "笑",
 "冲",
 "我",
 "笑",
 "百合",
 "百合花",
 "花开",
 "了",
 "野菊",
 "野菊花",
 "菊花",
 "也",
 "盛开",
 "了",
 "散发",
 "发着",
 "新",
 "的",
 "味道",
 "等",
 "你",
 "来",
 "等",
 "你",
 "来",
 "酒",
 "已",
 "开始",
 "在",
 "流淌",
 "流向",
 "醉人",
 "的",
 "地方",
 "依稀",
 "看见",
 "你",
 "的",
 "样子",
 "在",
 "前方",
 "在",
 "远方",
 "歌声",
 "已经",
 "走",
 "了",
 "走到",
 "听不见",
 "不见",
 "的",
 "地方",
 "是否",
 "能",
 "像",
 "花儿",
 "一样",
 "还",
 "会",
 "开",
 "还",
 "会",
 "开",
 "啦",
 "啦",
 "歌声",
 "已经",
 "走",
 "了",
 "走到",
 "听不见",
 "不见",
 "的",
 "地方",
 "是否",
 "能",
 "像",
 "花儿",
 "一样",
 "还",
 "会",
 "开",
 "还",
 "会",
 "开",
 "还",
 "会",
 "开",
 "还",
 "会",
 "开",
 "梦"]}