{"artist_name": "王力宏",
"song_name": "你的爱",
"song_id": "30070681",
"song_lyric":
 "作曲 : 王力宏\n 作词 : 王力宏\n已经多少年后 感觉像才发生过\n记得你说的话 记得你的温柔\n在烟雾弥漫中 握紧了你的手\n像是雨后出现彩虹 陪着我走\n一直到天长地久\n你的爱是唯一让我 坚持的理由\n不会再忘记你 存在我的心中\n你的爱是唯一让我 坚强的理由\n原来在你眼中 你从没放弃过我\n我终于才明了 你的爱多么重要\n再也不会离开 你温暖的怀抱\n世间的混乱中 感到你在身后\n就像天使般在微笑 分分秒秒\n一直到天荒地老\n你的爱是唯一让我 坚持的理由\n不会再忘记你 存在我的心中\n你的爱是唯一让我 坚强的理由\n原来在你眼中 你从没放弃过我\n决定要让你的爱 照亮我内心\n重新面对我自己 再也不怀疑\n你就是 所有意义\u2028\n所有原因\n你的爱是唯一让我 坚持的理由\n不会再忘记你 存在我的心中\n你的爱是唯一让我 坚强的理由\n原来在你眼中 你从没放弃过我",
"pic_url": "http://p1.music.126.net/W-WuxMMzuElnTYDCi5tx3w==/7788940371265685.jpg",
"words": ["作曲", "王力宏", "作词", "王力宏", "已经", "多少", "少年", "年后", "感觉", "像", "才", "发生", "生过", "记得", "你", "说", "的话", "记得", "你", "的", "温柔", "在", "烟雾", "烟雾弥漫", "弥漫", "中", "握紧", "了", "你", "的", "手", "像是", "雨后", "出现", "彩虹", "陪", "着", "我", "走", "一直", "直到", "天长", "天长地久", "地久", "你", "的", "爱", "是", "唯一", "让", "我", "坚持", "的", "理由", "不会", "再", "忘记", "你", "存在", "我", "的", "心中", "你", "的", "爱", "是", "唯一", "让", "我", "坚强", "的", "理由", "原来", "在", "你", "眼中", "你", "从没", "没放", "放弃", "过", "我", "我", "终于", "才", "明", "了", "你", "的", "爱多", "多么", "重要", "再也", "再也不会", "不会", "离开", "你", "温暖", "的", "怀抱", "世间", "的", "混乱", "中", "感到", "你", "在", "身后", "就", "像", "天使", "般", "在", "微笑", "分分", "分分秒秒", "分秒", "秒", "一直", "直到", "天荒地老", "荒地", "老", "你", "的", "爱", "是", "唯一", "让", "我", "坚持", "的", "理由", "不会", "再", "忘记", "你", "存在", "我", "的", "心中", "你", "的", "爱", "是", "唯一", "让", "我", "坚强", "的", "理由", "原来", "在", "你", "眼中", "你", "从没", "没放", "放弃", "过", "我", "决定", "定要", "让", "你", "的", "爱", "照亮", "我", "内心", "重新", "面对", "我", "自己", "再也", "不", "怀疑", "你", "就是", "所有", "有意", "意义", "所有", "原因", "你", "的", "爱", "是", "唯一", "让", "我", "坚持", "的", "理由", "不会", "再", "忘记", "你", "存在", "我", "的", "心中", "你", "的", "爱", "是", "唯一", "让", "我", "坚强", "的", "理由", "原来", "在", "你", "眼中", "你", "从没", "没放", "放弃", "过", "我"]}
