{"artist_name": "许美静",
"song_name": "听那星光歌唱",
"song_id": "306917",
"song_lyric":
 "作曲 : 陳佳明\n蓝蓝的风儿\t柔缓的夜晚\n茫茫人海\t有谁被遗忘\n远远的城市\t最爱的人哪\n遥遥相望\t同一个穹苍\n思念的深海总是永无止境\n相爱的季节总是遥不可及\n在睁开双眼之前\n一切都也许是梦幻\n听那漫天星光在歌唱\n犹如天使飞舞身旁\n世事无常\t人生难能圆满\n且莫再虚渡时光\n漫天的星光轻轻唱\n莫让光辉惊醒绸怅\n离合悲欢\t谁也不能移转\n且珍惜美梦一场\n蓝蓝的风儿\t柔缓的夜晚\n茫茫人海\t有谁被遗忘\n远远的城市\t最爱的人哪\n遥遥相望\t同一个穹苍\n思念的深海总是永无止境\n相爱的季节总是遥不可及\n在睁开双眼之前\n一切都也许是梦幻\n听那漫天星光在歌唱\n犹如天使飞舞身旁\n世事无常\t人生难能圆满\n且莫再虚渡时光\n漫天的星光轻轻唱\n莫让光辉惊醒绸怅\n离合悲欢\t谁也不能移转\n且珍惜美梦一场\n漫天的星光轻轻唱\n犹如天使飞舞身旁\n离合悲欢\t谁也不能移转\n且珍惜美梦一场\n离合悲欢\t谁也不能移转\n且珍惜美梦一场",
"pic_url": "http://p1.music.126.net/uziPToWeijIHJev_37YXcw==/67070209308602.jpg",
"words": ["作曲", "陳", "佳", "明", "蓝蓝", "蓝蓝的", "风儿", "柔", "缓", "的", "夜晚", "茫茫", "茫茫人海", "人海", "有", "谁", "被", "遗忘", "远远", "的", "城市", "最爱", "的", "人", "哪", "遥遥", "遥遥相望", "遥相", "相望", "同一", "同一个", "一个", "穹苍", "思念", "的", "深海", "总是", "永无", "永无止境", "无止境", "止境", "相爱", "的", "季节", "总是", "遥不可及", "不可", "及", "在", "睁开", "双眼", "之前", "一切", "都", "也许", "是", "梦幻", "听", "那", "漫天", "天星", "星光", "在", "歌唱", "犹如", "天使", "飞舞", "身旁", "世事", "无常", "人生", "难", "能", "圆满", "且莫", "再", "虚", "渡", "时光", "漫天", "的", "星光", "轻轻", "唱", "莫让", "光辉", "惊醒", "绸", "怅", "离合", "离合悲欢", "悲欢", "谁", "也", "不能", "移转", "且", "珍惜", "美梦", "一场", "蓝蓝", "蓝蓝的", "风儿", "柔", "缓", "的", "夜晚", "茫茫", "茫茫人海", "人海", "有", "谁", "被", "遗忘", "远远", "的", "城市", "最爱", "的", "人", "哪", "遥遥", "遥遥相望", "遥相", "相望", "同一", "同一个", "一个", "穹苍", "思念", "的", "深海", "总是", "永无", "永无止境", "无止境", "止境", "相爱", "的", "季节", "总是", "遥不可及", "不可", "及", "在", "睁开", "双眼", "之前", "一切", "都", "也许", "是", "梦幻", "听", "那", "漫天", "天星", "星光", "在", "歌唱", "犹如", "天使", "飞舞", "身旁", "世事", "无常", "人生", "难", "能", "圆满", "且莫", "再", "虚", "渡", "时光", "漫天", "的", "星光", "轻轻", "唱", "莫让", "光辉", "惊醒", "绸", "怅", "离合", "离合悲欢", "悲欢", "谁", "也", "不能", "移转", "且", "珍惜", "美梦", "一场", "漫天", "的", "星光", "轻轻", "唱", "犹如", "天使", "飞舞", "身旁", "离合", "离合悲欢", "悲欢", "谁", "也", "不能", "移转", "且", "珍惜", "美梦", "一场", "离合", "离合悲欢", "悲欢", "谁", "也", "不能", "移转", "且", "珍惜", "美梦", "一场"]}