{"artist_name": "郁可唯",
"song_name": "爱很简单",
"song_id": "316213",
"song_lyric":
 "忘了是怎么开始\n也许就是对你\n有一种感觉\n突然间发现自己\n已深深爱上你\n你真的很简单\n爱得地暗天黑都已无所谓\n是是非非无法决择\n没有后悔为爱日夜去跟随\n那个疯狂的人是我\n喔......\nI LOVE YOU\n无法不爱你BABY\n说你也爱我\nI LOVE YOU\n永远不愿意BABY\n失去你\n不可能更快乐\n只要能在一起\n做什么都可以\n虽然世界变个不停\n用最真诚的心\n让爱变得简单\n爱得地暗天黑都已无所谓\n是是非非无法决择\n没有后悔为爱日夜去跟随\n那个疯狂的人是我\n喔......\nI LOVE YOU\n无法不爱你BABY\n说你也爱我\nI LOVE YOU\n永远不愿意BABY\n失去你\n如果你还有一些困惑\nH NO\n请贴着我的心倾听\n听我说着爱你\nYES I DO\n\nI LOVE YOU\n一直在这里BABY\n一直在爱你\nI LOVE YOU\nYES I DO\n永远都不放弃\n这爱你的权利",
"pic_url": "http://p1.music.126.net/GPm_rSAUttPJpG_s6-zrNA==/111050674423367.jpg",
"words": ["忘", "了", "是", "怎么", "开始", "也许", "就是", "对", "你", "有", "一种", "感觉", "突然", "间", "发现", "发现自己", "自己", "已", "深深", "深爱", "爱上你", "你", "真的", "很", "简单", "爱", "得", "地", "暗", "天黑", "都", "已", "无所", "无所谓", "所谓", "是是非非", "是非", "非非", "无法", "决择", "没有", "后悔", "为", "爱", "日夜", "去", "跟随", "那个", "疯狂", "的", "人", "是", "我", "喔", "LOVE", "无法", "不", "爱", "你", "说", "你", "也", "爱", "我", "LOVE", "永远", "不", "愿意", "失去", "你", "不可", "可能", "更快", "快乐", "只要", "要能", "在", "一起", "做", "什么", "都", "可以", "虽然", "世界", "变", "个", "不停", "用", "最", "真诚", "的", "心", "让", "爱", "变得", "简单", "爱", "得", "地", "暗", "天黑", "都", "已", "无所", "无所谓", "所谓", "是是非非", "是非", "非非", "无法", "决择", "没有", "后悔", "为", "爱", "日夜", "去", "跟随", "那个", "疯狂", "的", "人", "是", "我", "喔", "LOVE", "无法", "不", "爱", "你", "说", "你", "也", "爱", "我", "LOVE", "永远", "不", "愿意", "失去", "你", "如果", "你", "还有", "一些", "困惑", "请贴", "贴着", "我", "的", "心", "倾听", "听", "我", "说", "着", "爱", "你", "I", "LOVE", "一直", "在", "这里", "一直", "在", "爱", "你", "LOVE", "I", "永远", "都", "不放", "放弃", "这", "爱", "你", "的", "权利"]}