{"artist_name": "不才",
 "song_name": "拿走了什么",
 "song_id": "34125772",
 "song_lyric": "拿走了什么\n\n猫常常望着窗口\n也发觉沙发上少个人\n曾经那样 被看好的我们\n隐身在彼此视线\n你变得 开朗\n她语带保留说你没落单\n你们幸福就好\n细节就不必对我交代\n我爱过几个人怎么还不够\n她们明明都比你更爱我\n你到底拿走了什么\n全世界都不说\n你说谎过几次都瞒不过我\n你诚实了为何我会难过\n你究竟拿走了什么\n让我 寂寞\n不管睡在床哪边\n都讽刺我你早已离开\n决心忘怀 是贴心的示范\n不干涉各自明天\n我要我 乐观\n不让共同朋友感觉为难\n好几次快笑场\n可怜自己成这副模样\n我爱过几个人怎么还不够\n她们明明都比你更爱我\n你究竟拿走了什么\n全世界都不说\n你说谎过几次都瞒不过我\n你诚实了为何我会难过\n你究竟拿走了什么\n让我 寂寞\n\n你说谎过几次都瞒不过我\n你诚实了为何我会难过\n你究竟拿走了什么\n让我 寂寞",
 "pic_url": "http://p1.music.126.net/SDYKlOH5UTUYRlM-Bo9l3g==/3411784581986489.jpg",
 "words": ["拿走",
 "了",
 "什么",
 "猫",
 "常常",
 "望",
 "着",
 "窗口",
 "也",
 "发觉",
 "沙发",
 "发上",
 "少",
 "个人",
 "曾经",
 "那样",
 "被",
 "看好",
 "的",
 "我们",
 "隐身",
 "在",
 "彼此",
 "视线",
 "你",
 "变得",
 "开朗",
 "她",
 "语",
 "带",
 "保留",
 "说",
 "你",
 "没落",
 "落单",
 "你们",
 "幸福",
 "就",
 "好",
 "细节",
 "就",
 "不必",
 "对",
 "我",
 "交代",
 "我",
 "爱",
 "过",
 "几个",
 "个人",
 "怎么",
 "还",
 "不够",
 "她们",
 "明明",
 "都",
 "比",
 "你",
 "更",
 "爱",
 "我",
 "你",
 "到底",
 "拿走",
 "了",
 "什么",
 "全世界",
 "世界",
 "都",
 "不",
 "说",
 "你",
 "说谎",
 "过",
 "几次",
 "都",
 "瞒不过",
 "不过",
 "我",
 "你",
 "诚实",
 "了",
 "为何",
 "我会",
 "难过",
 "你",
 "究竟",
 "拿走",
 "了",
 "什么",
 "让",
 "我",
 "寂寞",
 "不管",
 "睡",
 "在",
 "床",
 "哪边",
 "都",
 "讽刺",
 "我",
 "你",
 "早已",
 "离开",
 "决心",
 "忘怀",
 "是",
 "贴心",
 "的",
 "示范",
 "不",
 "干涉",
 "各自",
 "明天",
 "我",
 "要",
 "我",
 "乐观",
 "不让",
 "共同",
 "朋友",
 "感觉",
 "为难",
 "好几",
 "几次",
 "快",
 "笑场",
 "可怜",
 "自己",
 "成",
 "这",
 "副",
 "模样",
 "我",
 "爱",
 "过",
 "几个",
 "个人",
 "怎么",
 "还",
 "不够",
 "她们",
 "明明",
 "都",
 "比",
 "你",
 "更",
 "爱",
 "我",
 "你",
 "究竟",
 "拿走",
 "了",
 "什么",
 "全世界",
 "世界",
 "都",
 "不",
 "说",
 "你",
 "说谎",
 "过",
 "几次",
 "都",
 "瞒不过",
 "不过",
 "我",
 "你",
 "诚实",
 "了",
 "为何",
 "我会",
 "难过",
 "你",
 "究竟",
 "拿走",
 "了",
 "什么",
 "让",
 "我",
 "寂寞",
 "你",
 "说谎",
 "过",
 "几次",
 "都",
 "瞒不过",
 "不过",
 "我",
 "你",
 "诚实",
 "了",
 "为何",
 "我会",
 "难过",
 "你",
 "究竟",
 "拿走",
 "了",
 "什么",
 "让",
 "我",
 "寂寞"]}