{"artist_name": "回音哥",
"song_name": "扇子舞",
"song_id": "34218312",
"song_lyric":
 "啦啦啦啦啦啦啦\n粉红的扇子飞舞\n啦啦啦啦啦啦啦\n想和你一起漫步\n等爱的心跳多少速度\n像树上的知了歌唱此起彼伏\n想求求荷仙姑她替我占卜\n你是不是我护身符\n啊~\n和你相处心就会敲锣打鼓\n脸一直都红扑扑\n快快来降降温度\n啦啦啦啦啦啦啦\n粉红的扇子飞舞\n啦啦啦啦啦啦啦\n想和你一起漫步\n你怎么还不明白\n我等到花儿都要败\n把你的真心话都说出来\n虽然我心潮澎湃\n也不怕大太阳晒\n可是你的心到底在不在\n什么事情都变成典故\n你一句话情绪就天翻地覆\n快把我当成你的掌上明珠\n别辜负对你的爱慕\n啊~\n和你相处心就会敲锣打鼓\n脸一直都红扑扑\n快快来降降温度\n啦啦啦啦啦啦啦\n粉红的扇子飞舞\n啦啦啦啦啦啦啦\n想和你一起漫步\n你怎么还不明白\n我等到花儿都要败\n把你的真心话都说出来\n虽然我心潮澎湃\n也不怕大太阳晒\n可是你的心到底在不在\n我看不出来\n打开了这幕布\n就轮到我演出\n想为你边唱边跳\n扇子飞舞\n有你全神贯注\n我就会更投入\n不在乎付出多少汗珠\n泪珠不顾\n啦啦啦啦啦啦啦\n粉红的扇子飞舞\n啦啦啦啦啦啦啦\n想和你一起漫步\n你怎么还不明白\n粉红的扇子飞舞\n想和你一起漫步",
"pic_url": "http://p1.music.126.net/SDYKlOH5UTUYRlM-Bo9l3g==/3411784581986489.jpg",
"words": ["啦", "啦", "啦", "啦", "啦", "啦", "啦", "粉红", "的", "扇子", "飞舞", "啦", "啦", "啦", "啦", "啦", "啦", "啦", "想", "和", "你", "一起", "漫步", "等", "爱", "的", "心跳", "多少", "速度", "像", "树上", "的", "知", "了", "歌唱", "此起彼伏", "想", "求求", "荷", "仙姑", "她", "替", "我", "占卜", "你", "是不是", "不是", "我", "护身", "护身符", "啊", "和", "你", "相处", "心", "就", "会", "敲锣", "敲锣打鼓", "打鼓", "脸", "一直", "都", "红扑扑", "快快", "快来", "降降温", "降温", "温度", "啦", "啦", "啦", "啦", "啦", "啦", "啦", "粉红", "的", "扇子", "飞舞", "啦", "啦", "啦", "啦", "啦", "啦", "啦", "想", "和", "你", "一起", "漫步", "你", "怎么", "还", "不明", "明白", "我", "等到", "花儿", "都", "要", "败", "把", "你", "的", "真心", "真心话", "都", "说出", "出来", "虽然", "我心", "心潮", "心潮澎湃", "澎湃", "也", "不怕", "大", "太阳", "晒", "可是", "你", "的", "心", "到底", "在", "不在", "什么", "事情", "都", "变成", "典故", "你", "一句", "话", "情绪", "就", "天翻地覆", "翻地", "覆", "快", "把", "我", "当成", "你", "的", "掌上", "掌上明珠", "上明", "明珠", "别", "辜负", "对", "你", "的", "爱慕", "啊", "和", "你", "相处", "心", "就", "会", "敲锣", "敲锣打鼓", "打鼓", "脸", "一直", "都", "红扑扑", "快快", "快来", "降降温", "降温", "温度", "啦", "啦", "啦", "啦", "啦", "啦", "啦", "粉红", "的", "扇子", "飞舞", "啦", "啦", "啦", "啦", "啦", "啦", "啦", "想", "和", "你", "一起", "漫步", "你", "怎么", "还", "不明", "明白", "我", "等到", "花儿", "都", "要", "败", "把", "你", "的", "真心", "真心话", "都", "说出", "出来", "虽然", "我心", "心潮", "心潮澎湃", "澎湃", "也", "不怕", "大", "太阳", "晒", "可是", "你", "的", "心", "到底", "在", "不在", "我", "看不出", "看不出来", "不出", "出来", "打开", "了", "这", "幕布", "就", "轮到", "我", "演出", "想为", "你", "边", "唱", "边", "跳", "扇子", "飞舞", "有", "你", "全神", "全神贯注", "贯注", "我", "就", "会", "更", "投入", "不在", "不在乎", "在乎", "付出", "多少", "汗珠", "泪珠", "不顾", "啦", "啦", "啦", "啦", "啦", "啦", "啦", "粉红", "的", "扇子", "飞舞", "啦", "啦", "啦", "啦", "啦", "啦", "啦", "想", "和", "你", "一起", "漫步", "你", "怎么", "还", "不明", "明白", "粉红", "的", "扇子", "飞舞", "想", "和", "你", "一起", "漫步"]}