{"artist_name": "不才",
"song_name": "她",
"song_id": "35416253",
"song_lyric":
 "作曲 : 《摩登时代》\n哪个她\n在你心中是完美无瑕 做标榜\n逐一研习临摹才最佳 白月光\n水中倒影又惊炸开漩浪 供你臆想\n最亲昵一刹 绝似她\n暖的唇与温柔的情话 如蜜糖\n蝴蝶骨在昏黄壁灯下 被热望\n够无瑕 不够替代她 做你的光\n绝无仅有是梦想\n独一无二才信仰\n前人莫失莫忘\n去后如痴如狂\n譬如清白月光\n自古无双\n苦心经营假象 虔诚钻研荒唐\n唇齿间衔一枚谎\n吻过云端她诗行 切忌声张\n吻过心尖你激荡 以菲薄封缄虚妄\n赠你怀旧土壤 留取贪欢一晌\n暧昧过往拼凑来日方长\n潜移默化熔刻新形象\n抑或先烧尽渴望\n无非她\n天然风姿被回忆美化 难效仿\n街头巷尾八卦到声哑 太繁穣\n说笑罢 谁竟会惧怕 闲言毁谤\n苦心经营假象 虔诚钻研荒唐\n唇齿间衔一枚谎\n天堑未敢求同蹚 但问时光\n待铺就道路康庄 可愿并肩天梯上\n眉心颦蹙流光 鬓边点染风霜\n今夜熙攘又代入旧时光\n心尖烛火烧与你鉴赏\n竟算作如常 太寻常\n苦心经营假象 虔诚钻研荒唐\n唇齿间衔一枚谎\n吻过云端她诗行 切忌声张\n吻过心尖你激荡 以菲薄封缄虚妄\n眉心颦蹙流光 鬓边点染风霜\n今夜熙攘又代入旧时光\n心尖烛火烧与你鉴赏\n该认作如常 不寻常\n不必她\n得不到的身躯最无瑕 多薄凉\n曾失去的亲吻最牵挂 旧风光\n这一回 换我做她",
"pic_url": "http://p1.music.126.net/EnQ0J1f_-p8S2OunnRiGhA==/3298534885062503.jpg",
"words": ["作曲", "摩登", "摩登时代", "登时", "时代", "哪个", "她", "在", "你", "心中", "是", "完美", "完美无瑕", "无瑕", "做", "标榜", "逐一", "研习", "临摹", "才", "最佳", "白月光", "月光", "水中", "倒影", "又", "惊", "炸开", "漩", "浪", "供", "你", "臆想", "最", "亲昵", "一刹", "绝", "似", "她", "暖", "的", "唇", "与", "温柔", "的", "情话", "如", "蜜糖", "蝴蝶", "蝶骨", "在", "昏黄", "壁灯", "下", "被", "热望", "够", "无瑕", "不够", "替代", "她", "做", "你", "的", "光", "绝无", "绝无仅有", "是", "梦想", "独一", "独一无二", "才", "信仰", "前人", "莫", "失", "莫忘", "去", "后", "如痴如狂", "譬如", "清白", "白月光", "月光", "自古", "无双", "苦心", "苦心经营", "心经", "经营", "假象", "虔诚", "钻研", "荒唐", "唇齿", "齿间", "衔", "一枚", "谎", "吻", "过", "云端", "她", "诗行", "切忌", "声张", "吻", "过心", "心尖", "你", "激荡", "以", "菲薄", "封缄", "虚妄", "赠", "你", "怀旧", "土壤", "留取", "贪", "欢", "一", "晌", "暧昧", "过往", "拼凑", "来日", "来日方长", "日方", "长", "潜移", "潜移默化", "默化", "熔", "刻", "新", "形象", "抑或", "先", "烧尽", "渴望", "无非", "她", "天然", "风姿", "被", "回忆", "美化", "难", "效仿", "街头", "街头巷尾", "八卦", "到", "声", "哑", "太", "繁", "穣", "说", "笑", "罢", "谁", "竟", "会", "惧怕", "闲", "言", "毁谤", "苦心", "苦心经营", "心经", "经营", "假象", "虔诚", "钻研", "荒唐", "唇齿", "齿间", "衔", "一枚", "谎", "天堑", "未敢", "求同", "蹚", "但", "问", "时光", "待", "铺就", "道路", "康庄", "可愿", "并肩", "天梯", "上", "眉心", "颦", "蹙", "流光", "鬓边", "点染", "风霜", "今夜", "熙攘", "又", "代入", "旧时", "时光", "心尖", "烛火", "火烧", "与", "你", "鉴赏", "竟", "算作", "如常", "太", "寻常", "苦心", "苦心经营", "心经", "经营", "假象", "虔诚", "钻研", "荒唐", "唇齿", "齿间", "衔", "一枚", "谎", "吻", "过", "云端", "她", "诗行", "切忌", "声张", "吻", "过心", "心尖", "你", "激荡", "以", "菲薄", "封缄", "虚妄", "眉心", "颦", "蹙", "流光", "鬓边", "点染", "风霜", "今夜", "熙攘", "又", "代入", "旧时", "时光", "心尖", "烛火", "火烧", "与", "你", "鉴赏", "该", "认作", "如常", "不", "寻常", "不必", "她", "得不到", "不到", "的", "身躯", "最", "无瑕", "多", "薄", "凉", "曾", "失去", "的", "亲吻", "最", "牵挂", "旧", "风光", "这", "一回", "换", "我", "做", "她"]}
