{"artist_name": "G.E.M.邓紫棋",
"song_name": "来自天堂的魔鬼",
"song_id": "36270426",
"song_lyric":
 "作曲 : G.E.M.邓紫棋\n 作词 : G.E.M.邓紫棋\n\n夜里做了美丽的恶梦\n想清醒我却抵不过心动\n梦里你是无底的黑洞\n我无力抗拒失重\n我的意识自控脉搏流动\n全被你神秘引力操控\n亲爱的你是危险的迷宫\n我找不到出口\nYou took my heart away away away away\nMy head is blown away away away away\n你就是传说来自天堂的魔鬼\nYou should took my heart away away away away away away away\n拜托别对我细心问候\n这是你也不察觉的阴谋\n我讨厌你无心的微笑\n我快无可救药\n你像一个漩涡慢慢让我\n无法抽离一直地坠落\n亲爱的你是优雅的恶魔\n一点一点把我吞没\nYou took my heart away away away away\nMy head is blown away away away away\n你就是传说来自天堂的魔鬼\nYou should took my heart away away away away away away away\n如果你是蛇的诱惑\n你存心迷惑 我才能软弱\n但你是牛顿头上那颗\n若无其事的苹果\nYou took my heart away away away away\nYou took my heart away away away away\nYou took my heart away away away away\nMy head is blown away away away away\n你就是传说来自天堂的魔鬼\nYou should took my heart away away away away away away away",
"pic_url": "http://p1.music.126.net/kVwk6b8Qdya8oDyGDcyAVA==/1364493930777368.jpg",
"words": ["作曲", "G", "E", "M", "邓", "紫", "棋", "作词", "G", "E", "M", "邓", "紫", "棋", "夜里", "做", "了", "美丽", "的", "恶梦", "想", "清醒", "我", "却", "抵不过", "不过", "过心", "心动", "梦", "里", "你", "是", "无底", "的", "黑洞", "我", "无力", "抗拒", "失重", "我", "的", "意识", "自控", "脉搏", "流动", "全", "被", "你", "神秘", "引力", "操控", "亲爱", "的", "你", "是", "危险", "的", "迷宫", "我", "找", "不到", "出口", "took", "my", "heart", "away", "away", "away", "head", "is", "blown", "away", "away", "away", "你", "就是", "传说", "说来", "来自", "天堂", "的", "魔鬼", "should", "took", "my", "heart", "away", "away", "away", "away", "away", "away", "拜托", "别", "对", "我", "细心", "问候", "这", "是", "你", "也", "不察", "察觉", "的", "阴谋", "我", "讨厌", "你", "无心", "的", "微笑", "我", "快", "无可", "无可救药", "可救", "救药", "你", "像", "一个", "漩涡", "慢慢", "让", "我", "无法", "抽", "离", "一直", "地", "坠落", "亲爱", "的", "你", "是", "优雅", "的", "恶魔", "一点", "一点一点", "一点一点把", "一点", "把", "我", "吞没", "took", "my", "heart", "away", "away", "away", "head", "is", "blown", "away", "away", "away", "你", "就是", "传说", "说来", "来自", "天堂", "的", "魔鬼", "should", "took", "my", "heart", "away", "away", "away", "away", "away", "away", "如果", "你", "是", "蛇", "的", "诱惑", "你", "存心", "心迷", "迷惑", "我", "才能", "软弱", "但", "你", "是", "牛顿", "头上", "那", "颗", "若无", "若无其事", "其事", "的", "苹果", "took", "my", "heart", "away", "away", "away", "took", "my", "heart", "away", "away", "away", "took", "my", "heart", "away", "away", "away", "head", "is", "blown", "away", "away", "away", "你", "就是", "传说", "说来", "来自", "天堂", "的", "魔鬼", "should", "took", "my", "heart", "away", "away", "away", "away", "away", "away", "away"]}