{"artist_name": "小紫荆儿童合唱团",
"song_name": "狼来了",
"song_id": "388652",
"song_lyric":
 "天矇光牧羊人 迎著曙光不怕暗 帶領大羊群 向著前面山裡引\n登山看遠近 前面有一小市鎮 近見種田人 正在動力耕種\n(白)牧羊人坐系山崗上面 睇住0的羊系度食草鍋\n睇嚇睇嚇 櫃覺得好無聊 咁妠N念\n不如我同山下面0的人開個玩笑啦 於是 妠N大聲叫了\n有狼來啦 有狼來啦\n(唱)山邊的種田人 隨著叫聲跑上去 看見那牧羊人\n正在前面草地0訓 山邊的種田人 全部見到真氣憤\n要叫那牧羊人 最後承受好教訓",
"pic_url": "http://p1.music.126.net/ew3I_rmId_K8h_ktbm3GlA==/3125911557843174.jpg",
"words": ["天", "矇", "光", "牧羊", "牧羊人", "迎", "著", "曙光", "不怕", "暗", "帶", "領", "大", "羊群", "向", "著", "前面", "面山", "裡", "引", "登山", "看", "遠", "近", "前面", "面有", "一小", "小市", "鎮", "近", "見", "種", "田", "人", "正在", "動", "力", "耕", "種", "白", "牧羊", "牧羊人", "坐", "系", "山", "崗", "上面", "睇", "住", "0", "的", "羊", "系", "度", "食草", "鍋", "睇", "嚇", "睇", "嚇", "櫃", "覺", "得", "好", "無", "聊", "咁", "妠", "N", "念", "不如", "我", "同", "山下", "下面", "0", "的", "人", "開", "個", "玩笑", "啦", "於", "是", "妠", "N", "大", "聲", "叫", "了", "有", "狼", "來", "啦", "有", "狼", "來", "啦", "唱", "山", "邊", "的", "種", "田", "人", "隨", "著", "叫", "聲", "跑", "上去", "看", "見", "那", "牧羊", "牧羊人", "正在", "前面", "草地", "0", "訓", "山", "邊", "的", "種", "田", "人", "全部", "見", "到", "真", "氣", "憤", "要", "叫", "那", "牧羊", "牧羊人", "最", "後", "承受", "好", "教", "訓"]}
