{"artist_name": "自然卷",
 "song_name": "风和日丽 (男生版)",
 "song_id": "394520",
 "song_lyric": "八月八日天气晴\n三十六度Ｃ\n还不够煮熟一只鸭子\n你就飞了\n好在今天风和日丽\n决定暂时把你\n忘得一乾二净\n\n二月十四天气晴\n十八度Ｃ\n来不及溶化一幅雪景\n你就说你爱我\n真的爱我\n全都因为这样的天气\n喔\xa0原谅变得容易\n喔\xa0大声说出心里的话\n仰望蓝天白云\n眯着眼睛\n世界更清晰\n\n四月二十三天气晴\n三十二度Ｃ\n刚好可以养只鲸鱼\n你说要去旅行\n要去巴黎\n听手风琴\n听说现在那里\n风和日丽\n喔\xa0对自己好一点\n喔\xa0连续喝上十杯咖啡\n喔\xa0洒点香水\n换上高跟鞋\n今天要去打猎\n喔\xa0RIDE\xa0ON\xa0MY\xa0BICYCLE\n从台北到高雄也不会累\n仰望蓝天白云\n眯着眼睛\nMAKE\xa0SOME\xa0WISH\n世界更美丽",
 "pic_url": "http://p1.music.126.net/L-2MtlhyMOE0batfpWMIyw==/638816255750145.jpg",
 "words": ["八月",
 "八月八",
 "八日",
 "天气",
 "晴",
 "三十",
 "三十六",
 "十六",
 "十六度",
 "六度",
 "还",
 "不够",
 "煮熟",
 "一只",
 "鸭子",
 "你",
 "就",
 "飞",
 "了",
 "好",
 "在",
 "今天",
 "风和日丽",
 "日丽",
 "决定",
 "暂时",
 "把",
 "你",
 "忘",
 "得",
 "一乾二净",
 "二月",
 "十四",
 "十四天",
 "四天",
 "天气",
 "晴",
 "十八",
 "八度",
 "来不及",
 "不及",
 "溶化",
 "一幅",
 "雪景",
 "你",
 "就",
 "说",
 "你",
 "爱",
 "我",
 "真的",
 "爱",
 "我",
 "全都",
 "因为",
 "这样",
 "的",
 "天气",
 "喔",
 "原谅",
 "变得",
 "容易",
 "喔",
 "大声",
 "说出",
 "心里",
 "的话",
 "仰望",
 "蓝天",
 "蓝天白云",
 "白云",
 "眯着",
 "眯着眼",
 "着眼",
 "眼睛",
 "世界",
 "更",
 "清晰",
 "四月",
 "二十",
 "二十三",
 "十三",
 "十三天",
 "三天",
 "天气",
 "晴",
 "三十",
 "三十二",
 "三十二度",
 "十二",
 "十二度",
 "二度",
 "刚好",
 "可以",
 "养",
 "只",
 "鲸鱼",
 "你",
 "说",
 "要",
 "去",
 "旅行",
 "要",
 "去",
 "巴黎",
 "听",
 "手风",
 "手风琴",
 "风琴",
 "听说",
 "现在",
 "那里",
 "风和日丽",
 "日丽",
 "喔",
 "对",
 "自己",
 "好",
 "一点",
 "喔",
 "连续",
 "喝",
 "上",
 "十杯",
 "咖啡",
 "喔",
 "洒",
 "点",
 "香水",
 "换上",
 "上高",
 "高跟鞋",
 "今天",
 "要",
 "去",
 "打猎",
 "喔",
 "RIDE",
 "ON",
 "MY",
 "从",
 "台北",
 "到",
 "高",
 "雄",
 "也",
 "不会",
 "累",
 "仰望",
 "蓝天",
 "蓝天白云",
 "白云",
 "眯着",
 "眯着眼",
 "着眼",
 "眼睛",
 "SOME",
 "世界",
 "更",
 "美丽"]}