{"artist_name": "陈绮贞",
"song_name": "我喜欢上你时的内心活动",
"song_id": "471403427",
"song_lyric":
 "作曲 : 陈光荣\n 作词 : 韩寒\n编曲：陈光荣\n在九月 潮湿的车厢\n你看着车窗\n窗外它，水管在开花\n椅子在异乡\n树叶有翅膀\n上海的街道\n雪山在边上\n你靠着车窗\n我心脏一旁\n我们去哪\n你看那，九点钟方向\n日内瓦湖的房子贵吗\n世界上，七千个地方\n我们定居哪\n告诉我，答案是什么\n你喜欢去哪\n青海或三亚\n冰岛或希腊\n南美不去吗\n沙漠你爱吗\n我问太多了\n知道吗，这里的雨季只有一两天\n白昼很长，也很短\n夜晚有三年\n知道嘛，今天的消息\n说一号公路上\n那座桥断了\n我们还去吗\n要不再说呢\n会修一年吧\n一年能等吗\n你还去吗\n你喜欢吗\n\n监制：陈光荣\nOP : Click Music Ltd.\n\n制作及发行公司：Click Music Ltd.\n电影音乐推广：奔跑怪物",
"pic_url": "http://p1.music.126.net/AyyxC4stCu-Pm5qa8gaqDQ==/18762066418246617.jpg",
"words": ["作曲", "陈", "光荣", "作词", "韩", "寒", "编曲", "陈", "光荣", "在", "九月", "潮湿", "的", "车厢", "你", "看着", "车窗", "窗外", "它", "水管", "在", "开花", "椅子", "在", "异乡", "树叶", "有", "翅膀", "上海", "的", "街道", "雪山", "在", "边上", "你", "靠着", "车窗", "我心", "心脏", "一旁", "我们", "去", "哪", "你", "看", "那", "九点", "九点钟", "点钟", "方向", "日内瓦", "日内瓦湖", "的", "房子", "贵", "吗", "世界", "上", "七千", "千个", "地方", "我们", "定居", "哪", "告诉", "我", "答案", "是", "什么", "你", "喜欢", "去", "哪", "青海", "或", "三亚", "冰岛", "或", "希腊", "南美", "不", "去", "吗", "沙漠", "你", "爱", "吗", "我", "问", "太多", "了", "知道", "吗", "这里", "的", "雨季", "只有", "一两", "一两天", "两天", "白昼", "很", "长", "也", "很", "短", "夜晚", "有", "三年", "知道", "嘛", "今天", "的", "消息", "说", "一号", "公路", "路上", "那", "座", "桥", "断", "了", "我们", "还", "去", "吗", "要", "不再", "再说", "呢", "会", "修", "一年", "吧", "一年", "能", "等", "吗", "你", "还", "去", "吗", "你", "喜欢", "吗", "监制", "陈", "光荣", "Click", "Music", "Ltd", "制作", "及", "发行", "公司", "Click", "Music", "Ltd", "电影", "影音", "音乐", "推广", "奔跑", "怪物"]}