{"artist_name": "光良",
"song_name": "女孩别哭",
"song_id": "85451",
"song_lyric":
 "猜猜 谁让你的心痛\n谁让你的泪流\n我能做什么\n轻轻 安慰你的心痛\n吹干你的伤口\n自己痛却不能说出口\n相遇的不是时候\n为何我在他之后\n只能当你的听众\n谈心的朋友\n想哭的不是时候\n总在你受伤之后\n我的泪留着以后再说\n\n女孩别哭\n有什么难过对我说\n女孩别哭\n我不愿看见你泪流\n忍住泪\n就算一辈子\n我只能做你的朋友\n女孩别哭\n有眼泪让我为你流\n\n轻轻 安慰你的心痛\n吹干你的伤口\n自己痛却不能说出口\n相遇的不是时候\n为何我在他之后\n只能当你的听众\n谈心的朋友\n想哭的不是时候\n总在你受伤之后\n我的泪留着以后再说\n女孩别哭\n有什么难过对我说\n女孩别哭\n我不愿看见你泪流\n忍住泪\n就算一辈子\n我只能做你的朋友\n女孩别哭\n有眼泪让我为你流\n女孩别哭\n他犯的错我来承受\n女孩别哭\n我的手来掩你的痛\n忍住泪\n就算一辈子\n我只能做你的朋友\n女孩别哭\n有眼泪让我为你流",
"pic_url": "http://p1.music.126.net/EsPx4aOtnDFewtIXZVH42g==/18625726976227920.jpg",
"words": ["猜猜", "谁", "让", "你", "的", "心痛", "谁", "让", "你", "的", "泪流", "我", "能", "做", "什么", "轻轻", "安慰", "你", "的", "心痛", "吹干", "你", "的", "伤口", "自己", "痛", "却", "不能", "说出", "出口", "相遇", "的", "不是", "时候", "为何", "我", "在", "他", "之后", "只能", "当", "你", "的", "听众", "谈心", "的", "朋友", "想", "哭", "的", "不是", "时候", "总", "在", "你", "受伤", "之后", "我", "的", "泪", "留", "着", "以后", "再说", "女孩", "别哭", "有", "什么", "难过", "对", "我", "说", "女孩", "别哭", "我", "不", "愿", "看见", "你", "泪流", "忍住", "泪", "就算", "一辈", "一辈子", "辈子", "我", "只能", "做", "你", "的", "朋友", "女孩", "别哭", "有", "眼泪", "让", "我", "为", "你", "流", "轻轻", "安慰", "你", "的", "心痛", "吹干", "你", "的", "伤口", "自己", "痛", "却", "不能", "说出", "出口", "相遇", "的", "不是", "时候", "为何", "我", "在", "他", "之后", "只能", "当", "你", "的", "听众", "谈心", "的", "朋友", "想", "哭", "的", "不是", "时候", "总", "在", "你", "受伤", "之后", "我", "的", "泪", "留", "着", "以后", "再说", "女孩", "别哭", "有", "什么", "难过", "对", "我", "说", "女孩", "别哭", "我", "不", "愿", "看见", "你", "泪流", "忍住", "泪", "就算", "一辈", "一辈子", "辈子", "我", "只能", "做", "你", "的", "朋友", "女孩", "别哭", "有", "眼泪", "让", "我", "为", "你", "流", "女孩", "别哭", "他", "犯", "的", "错", "我", "来", "承受", "女孩", "别哭", "我", "的", "手", "来", "掩", "你", "的", "痛", "忍住", "泪", "就算", "一辈", "一辈子", "辈子", "我", "只能", "做", "你", "的", "朋友", "女孩", "别哭", "有", "眼泪", "让", "我", "为", "你", "流"]}
